[{"序號":1,"國別地區":["南韓"],"中文片名":"鬼病院：靈異直播","上映日期":"2018/04/20","申請人":"車庫娛樂股份有限公司","出品":["SHOWBOX CORP"],"上映院數":"39","銷售票數":"35,725","銷售金額":"8,140,189","金額變動率":"56.09%","累計銷售票數":"58,460","累計銷售金額":"13,355,331","洲別":["亞洲"]},{"序號":2,"國別地區":["美國"],"中文片名":"圍雞總動員","上映日期":"2018/04/20","申請人":"美商美國環球影片股份有限公司台灣分公司","出品":["UNIVERSAL INTERNATIONAL FILMS LLC"],"上映院數":"77","銷售票數":"29,932","銷售金額":"6,813,697","金額變動率":"-14.15%","累計銷售票數":"64,736","累計銷售金額":"14,750,495","洲別":["北美洲"]},{"序號":3,"國別地區":["法國"],"中文片名":"厄夢娃娃屋","上映日期":"2018/04/20","申請人":"双喜電影發行股份有限公司","出品":["KINOLOGY"],"上映院數":"38","銷售票數":"4,630","銷售金額":"1,072,151","金額變動率":"-18.36%","累計銷售票數":"10,284","累計銷售金額":"2,385,341","洲別":["歐洲"]},{"序號":4,"國別地區":["法國"],"中文片名":"獨帆之聲","上映日期":"2018/04/20","申請人":"采昌國際多媒體股份有限公司","出品":["STUDIOCANAL"],"上映院數":"33","銷售票數":"2,484","銷售金額":"546,662","金額變動率":"-39.65%","累計銷售票數":"6,367","累計銷售金額":"1,452,419","洲別":["歐洲"]},{"序號":5,"國別地區":["日本"],"中文片名":"反叛的魯路修I興道","上映日期":"2018/04/20","申請人":"香港商甲上娛樂有限公司台灣分公司","出品":["株式会社サンライズ"],"上映院數":"6","銷售票數":"1,908","銷售金額":"469,807","金額變動率":"-42.35%","累計銷售票數":"5,241","累計銷售金額":"1,284,730","洲別":["亞洲"]},{"序號":6,"國別地區":["義大利"],"中文片名":"人生無限露營車","上映日期":"2018/04/20","申請人":"傳影互動股份有限公司","出品":["BAC FILMS DISTRIBUTION"],"上映院數":"11","銷售票數":"1,888","銷售金額":"403,632","金額變動率":"0.09%","累計銷售票數":"3,737","累計銷售金額":"806,887","洲別":["歐洲"]},{"序號":7,"國別地區":["英國"],"中文片名":"只殺陌生人","上映日期":"2018/04/20","申請人":"英屬蓋曼群島商威望國際娛樂股份有限公司台灣分公司","出品":["ANTON PICTURES S A R L"],"上映院數":"43","銷售票數":"1,461","銷售金額":"326,384","金額變動率":"-62.85%","累計銷售票數":"5,383","累計銷售金額":"1,204,923","洲別":["歐洲"]},{"序號":8,"國別地區":["匈牙利"],"中文片名":"天使追殺令","上映日期":"2018/04/20","申請人":"海鵬影業有限公司","出品":["THE MATCH FACTORY GMBH"],"上映院數":"10","銷售票數":"1,281","銷售金額":"272,935","金額變動率":"-20.03%","累計銷售票數":"2,823","累計銷售金額":"614,235","洲別":["歐洲"]},{"序號":9,"國別地區":["南韓"],"中文片名":"野蠻公主玩婚記","上映日期":"2018/04/20","申請人":"華聯國際影音股份有限公司","出品":["CJ E & M CORPORATION"],"上映院數":"25","銷售票數":"1,223","銷售金額":"258,429","金額變動率":"-56.90%","累計銷售票數":"4,052","累計銷售金額":"901,132","洲別":["亞洲"]},{"序號":10,"國別地區":["日本"],"中文片名":"齊木楠雄的災難","上映日期":"2018/04/20","申請人":"天馬行空數位有限公司","出品":["NIPPON TELEVISION NETWORK CORPORATION"],"上映院數":"6","銷售票數":"689","銷售金額":"165,446","金額變動率":"-44.67%","累計銷售票數":"1,907","累計銷售金額":"464,464","洲別":["亞洲"]},{"序號":11,"國別地區":["俄羅斯"],"中文片名":"冰上情緣","上映日期":"2018/04/20","申請人":"車庫娛樂股份有限公司","出品":["LIMITED COMPANY ART PICTURES STUDIO"],"上映院數":"12","銷售票數":"315","銷售金額":"69,320","金額變動率":"-33.84%","累計銷售票數":"768","累計銷售金額":"174,093","洲別":["亞洲"]},{"序號":12,"國別地區":["日本"],"中文片名":"東京日和","上映日期":"2018/04/20","申請人":"輝洪開發股份有限公司","出品":["FUJITELEVISON NETWORKS INC"],"上映院數":"2","銷售票數":"328","銷售金額":"67,475","金額變動率":"20.06%","累計銷售票數":"594","累計銷售金額":"123,675","洲別":["亞洲"]},{"序號":13,"國別地區":["義大利"],"中文片名":"愛在盡頭遇見你","上映日期":"2018/04/20","申請人":"聯影企業股份有限公司","出品":["FANDANGO SPA"],"上映院數":"5","銷售票數":"334","銷售金額":"67,130","金額變動率":"10.28%","累計銷售票數":"640","累計銷售金額":"128,005","洲別":["歐洲"]},{"序號":14,"國別地區":["日本"],"中文片名":"未成年愛狠大","上映日期":"2018/04/20","申請人":"車庫娛樂股份有限公司","出品":["TOHO CO LTD"],"上映院數":"4","銷售票數":"184","銷售金額":"42,735","金額變動率":"-46.44%","累計銷售票數":"540","累計銷售金額":"122,530","洲別":["亞洲"]},{"序號":15,"國別地區":["中華民國"],"中文片名":"嫐","上映日期":"2018/04/20","申請人":"金大立電影企業股份有限公司","出品":["金大立電影企業股份有限公司"],"上映院數":"7","銷售票數":"139","銷售金額":"31,025","金額變動率":"-18.81%","累計銷售票數":"309","累計銷售金額":"69,240","洲別":["亞洲"]},{"序號":16,"國別地區":["香港"],"中文片名":"脫皮爸爸","上映日期":"2018/04/20","申請人":"可樂藝術文創股份有限公司","出品":["幻 國影業有限公司","北京劇角映畫文化傳媒股份有限公司","大地時代文化傳播有限公司","邵氏兄弟國際影業有限公司","北京啓泰遠洋文化傳媒有限公司","宇鯉影業有限公司","北京劇魔影業投資管理有限公司","壹睿諮詢有限公司"],"上映院數":"4","銷售票數":"89","銷售金額":"16,700","金額變動率":"1,013.33%","累計銷售票數":"98","累計銷售金額":"18,200","洲別":["亞洲"]},{"序號":17,"國別地區":["西班牙"],"中文片名":"破處驚魂夜","上映日期":"2018/04/20","申請人":"暗光鳥有限公司","出品":["JINGA FILMS LTD"],"上映院數":"2","銷售票數":"18","銷售金額":"3,715","金額變動率":"-13.70%","累計銷售票數":"39","累計銷售金額":"8,020","洲別":["歐洲"]},{"序號":18,"國別地區":["美國"],"中文片名":"撕裂遊戲","上映日期":"2018/04/20","申請人":"暗光鳥有限公司","出品":["JINGA FILMS LTD"],"上映院數":"2","銷售票數":"2","銷售金額":"410","金額變動率":"-85.04%","累計銷售票數":"15","累計銷售金額":"3,150","洲別":["北美洲"]},{"序號":19,"國別地區":["中華民國"],"中文片名":"盛情款待","上映日期":"2018/04/13","申請人":"天大影業股份有限公司","出品":["天大影業股份有限公司","株式会社松竹撮影所"],"上映院數":"20","銷售票數":"1,307","銷售金額":"278,090","金額變動率":"-65.52%","累計銷售票數":"10,177","累計銷售金額":"2,168,914","洲別":["亞洲"]},{"序號":20,"國別地區":["美國"],"中文片名":"真愛趁現在","上映日期":"2018/04/13","申請人":"威視股份有限公司","出品":["MIDNIGHT SUN LLC"],"上映院數":"32","銷售票數":"805","銷售金額":"184,808","金額變動率":"-87.26%","累計銷售票數":"13,175","累計銷售金額":"3,083,896","洲別":["北美洲"]},{"序號":21,"國別地區":["英國"],"中文片名":"春光之境","上映日期":"2018/04/13","申請人":"車庫娛樂股份有限公司","出品":["PROTAGONIST PICTURES LTD"],"上映院數":"4","銷售票數":"221","銷售金額":"48,090","金額變動率":"-63.60%","累計銷售票數":"1,341","累計銷售金額":"291,900","洲別":["歐洲"]},{"序號":22,"國別地區":["美國"],"中文片名":"最後相愛的日子","上映日期":"2018/04/13","申請人":"英屬蓋曼群島商威望國際娛樂股份有限公司台灣分公司","出品":["IM GLOBAL LLC"],"上映院數":"9","銷售票數":"226","銷售金額":"46,090","金額變動率":"-77.80%","累計銷售票數":"2,273","累計銷售金額":"478,449","洲別":["北美洲"]},{"序號":23,"國別地區":["法國"],"中文片名":"我的美麗爸爸","上映日期":"2018/04/13","申請人":"佳映娛樂國際股份有限公司","出品":["DOC & FILM INTERNATIONAL"],"上映院數":"4","銷售票數":"70","銷售金額":"13,465","金額變動率":"-55.75%","累計銷售票數":"334","累計銷售金額":"66,495","洲別":["歐洲"]},{"序號":24,"國別地區":["美國"],"中文片名":"底特律","上映日期":"2018/04/13","申請人":"車庫娛樂股份有限公司","出品":["METRO-GOLDWYN-"],"上映院數":"5","銷售票數":"50","銷售金額":"11,575","金額變動率":"-89.01%","累計銷售票數":"1,028","累計銷售金額":"241,166","洲別":["北美洲"]},{"序號":25,"國別地區":["義大利"],"中文片名":"裸色愛情","上映日期":"2018/04/13","申請人":"佳映娛樂國際股份有限公司","出品":["CELLULOID DREAMS SAS"],"上映院數":"4","銷售票數":"56","銷售金額":"10,535","金額變動率":"-71.57%","累計銷售票數":"413","累計銷售金額":"79,100","洲別":["歐洲"]},{"序號":26,"國別地區":["義大利"],"中文片名":"給自己的情書","上映日期":"2018/04/13","申請人":"佳映娛樂國際股份有限公司","出品":["TRUE COLOURS GLORIOUS FILMS S R L"],"上映院數":"3","銷售票數":"47","銷售金額":"8,935","金額變動率":"-62.57%","累計銷售票數":"287","累計銷售金額":"55,480","洲別":["歐洲"]},{"序號":27,"國別地區":["墨西哥"],"中文片名":"四月的女兒","上映日期":"2018/04/13","申請人":"天馬行空數位有限公司","出品":["MK2 FILMS"],"上映院數":"3","銷售票數":"35","銷售金額":"8,080","金額變動率":"-81.78%","累計銷售票數":"492","累計銷售金額":"106,065","洲別":["北美洲"]},{"序號":28,"國別地區":["美國"],"中文片名":"自殺實境秀","上映日期":"2018/04/13","申請人":"暗光鳥有限公司","出品":["GREAT POINT MEDIA LTD"],"上映院數":"1","銷售票數":"11","銷售金額":"2,380","金額變動率":"-80.55%","累計銷售票數":"168","累計銷售金額":"35,880","洲別":["北美洲"]},{"序號":29,"國別地區":["加拿大"],"中文片名":"11號戰壕","上映日期":"2018/04/13","申請人":"暗光鳥有限公司","出品":["RAVEN BANNER ENTERTAINMENT INC"],"上映院數":"1","銷售票數":"5","銷售金額":"1,080","金額變動率":"-86.79%","累計銷售票數":"84","累計銷售金額":"17,735","洲別":["北美洲"]},{"序號":30,"國別地區":["泰國"],"中文片名":"禮物","上映日期":"2018/04/13","申請人":"鴻基國際視訊股份有限公司","出品":["GDH 599 COMPANY LTD"],"上映院數":"1","銷售票數":"2","銷售金額":"540","金額變動率":"-86.96%","累計銷售票數":"40","累計銷售金額":"9,900","洲別":["亞洲"]},{"序號":31,"國別地區":["日本"],"中文片名":"衝吧！我的龐克青春","上映日期":"2018/04/13","申請人":"鴻基國際視訊股份有限公司","出品":["COLORBIRD INC"],"上映院數":"1","銷售票數":"0","銷售金額":"0","金額變動率":"-100.00%","累計銷售票數":"53","累計銷售金額":"11,540","洲別":["亞洲"]},{"序號":32,"國別地區":["美國"],"中文片名":"毀滅大作戰","上映日期":"2018/04/12","申請人":"美商華納兄弟（遠東）股份有限公司台灣分公司","出品":["WARNER BROS PICTURES INTERNATIONAL"],"上映院數":"92","銷售票數":"69,022","銷售金額":"15,915,715","金額變動率":"-65.63%","累計銷售票數":"503,627","累計銷售金額":"118,668,044","洲別":["北美洲"]},{"序號":33,"國別地區":["法國"],"中文片名":"終極殺陣5","上映日期":"2018/04/12","申請人":"海樂影業股份有限公司","出品":["T5 PRODUCTION"],"上映院數":"67","銷售票數":"11,457","銷售金額":"2,576,179","金額變動率":"-74.18%","累計銷售票數":"106,680","累計銷售金額":"24,102,761","洲別":["歐洲"]},{"序號":34,"國別地區":["美國"],"中文片名":"噤界","上映日期":"2018/04/04","申請人":"美商美國派拉蒙影片股份有限公司台灣分公司","出品":["PARAMOUNT PICTURES CORPORATION"],"上映院數":"81","銷售票數":"14,154","銷售金額":"3,352,497","金額變動率":"-67.78%","累計銷售票數":"300,510","累計銷售金額":"69,764,650","洲別":["北美洲"]},{"序號":35,"國別地區":["南韓"],"中文片名":"雨妳再次相遇","上映日期":"2018/04/04","申請人":"車庫娛樂股份有限公司","出品":["LOTTE ENTERTAINMENT"],"上映院數":"40","銷售票數":"4,317","銷售金額":"992,847","金額變動率":"-65.84%","累計銷售票數":"76,519","累計銷售金額":"17,671,083","洲別":["亞洲"]},{"序號":36,"國別地區":["美國"],"中文片名":"比得兔","上映日期":"2018/04/04","申請人":"博偉電影股份有限公司","出品":["SONY PICTURES RELEASING INTERNATIONAL CORPORATION"],"上映院數":"63","銷售票數":"3,176","銷售金額":"716,126","金額變動率":"-70.97%","累計銷售票數":"115,171","累計銷售金額":"26,234,286","洲別":["北美洲"]},{"序號":37,"國別地區":["英國"],"中文片名":"寂寞大師","上映日期":"2018/04/04","申請人":"傳影互動股份有限公司","出品":["HANWAY FILMS LTD"],"上映院數":"5","銷售票數":"248","銷售金額":"52,705","金額變動率":"-73.61%","累計銷售票數":"7,002","累計銷售金額":"1,560,219","洲別":["歐洲"]},{"序號":38,"國別地區":["美國"],"中文片名":"糯爾摩斯","上映日期":"2018/04/04","申請人":"美商美國派拉蒙影片股份有限公司台灣分公司","出品":["PARAMOUNT PICTURES CORPORATION"],"上映院數":"9","銷售票數":"88","銷售金額":"19,445","金額變動率":"-90.88%","累計銷售票數":"22,027","累計銷售金額":"4,999,785","洲別":["北美洲"]},{"序號":39,"國別地區":["美國"],"中文片名":"恩德培行動","上映日期":"2018/04/04","申請人":"英屬維京群島商高捷全球開發有限公司 台灣分公司","出品":["STORYTELLER DISTRIBUTION CO LLC"],"上映院數":"5","銷售票數":"48","銷售金額":"11,260","金額變動率":"-93.97%","累計銷售票數":"25,027","累計銷售金額":"5,666,197","洲別":["北美洲"]},{"序號":40,"國別地區":["日本"],"中文片名":"特別版FREE！男子游泳部－TAKEYOURMARKS－","上映日期":"2018/04/04","申請人":"采昌國際多媒體股份有限公司","出品":["ABC ANIMATION INC"],"上映院數":"6","銷售票數":"43","銷售金額":"9,800","金額變動率":"-90.52%","累計銷售票數":"10,269","累計銷售金額":"2,530,721","洲別":["亞洲"]},{"序號":41,"國別地區":["挪威"],"中文片名":"魔女席瑪","上映日期":"2018/04/04","申請人":"鏡象電影製作有限公司","出品":["MEMENTO FILMS INTERNATIONAL"],"上映院數":"1","銷售票數":"9","銷售金額":"2,150","金額變動率":"-93.99%","累計銷售票數":"2,410","累計銷售金額":"539,236","洲別":["歐洲"]},{"序號":42,"國別地區":["法國"],"中文片名":"最酷的旅伴","上映日期":"2018/04/03","申請人":"海鵬影業有限公司","出品":["FREEWAY ENTERTAINMENT KFT"],"上映院數":"8","銷售票數":"1,384","銷售金額":"296,940","金額變動率":"-38.97%","累計銷售票數":"11,822","累計銷售金額":"2,538,250","洲別":["歐洲"]},{"序號":43,"國別地區":["法國"],"中文片名":"卡拉絲：為愛而聲","上映日期":"2018/04/03","申請人":"采昌國際多媒體股份有限公司","出品":["MK2 FILMS-SOCIÉTÉ PAR ACTIONS SIMPLIFIÉE"],"上映院數":"3","銷售票數":"26","銷售金額":"5,750","金額變動率":"-94.49%","累計銷售票數":"3,774","累計銷售金額":"812,123","洲別":["歐洲"]},{"序號":44,"國別地區":["中華民國"],"中文片名":"有一種喜歡","上映日期":"2018/03/30","申請人":"九星電影有限公司","出品":["九星電影有限公司","風山漸有限公司"],"上映院數":"11","銷售票數":"185","銷售金額":"41,275","金額變動率":"-88.02%","累計銷售票數":"39,354","累計銷售金額":"8,847,266","洲別":["亞洲"]},{"序號":45,"國別地區":["日本"],"中文片名":"劇場版無敵鐵金剛/INFINITY","上映日期":"2018/03/30","申請人":"曼迪傳播有限公司","出品":["TOEI ANIMATION CO LTD"],"上映院數":"8","銷售票數":"97","銷售金額":"23,125","金額變動率":"-86.67%","累計銷售票數":"29,204","累計銷售金額":"6,888,674","洲別":["亞洲"]},{"序號":46,"國別地區":["日本"],"中文片名":"多桑不在家","上映日期":"2018/03/30","申請人":"天馬行空數位有限公司","出品":["CREI INC"],"上映院數":"1","銷售票數":"25","銷售金額":"5,220","金額變動率":"-84.33%","累計銷售票數":"5,665","累計銷售金額":"1,240,575","洲別":["亞洲"]},{"序號":47,"國別地區":["南韓"],"中文片名":"消屍的夜晚","上映日期":"2018/03/30","申請人":"車庫娛樂股份有限公司","出品":["CONTENTS PANDA"],"上映院數":"1","銷售票數":"0","銷售金額":"0","金額變動率":"-100.00%","累計銷售票數":"5,250","累計銷售金額":"1,192,363","洲別":["亞洲"]},{"序號":48,"國別地區":["美國"],"中文片名":"一級玩家","上映日期":"2018/03/29","申請人":"美商華納兄弟（遠東）股份有限公司台灣分公司","出品":["WARNER BROS PICTURES INTERNATIONAL"],"上映院數":"90","銷售票數":"49,309","銷售金額":"12,572,988","金額變動率":"-62.94%","累計銷售票數":"1,338,563","累計銷售金額":"345,285,429","洲別":["北美洲"]},{"序號":49,"國別地區":["中國大陸"],"中文片名":"七月與安生","上映日期":"2018/03/23","申請人":"香港商甲上娛樂有限公司台灣分公司","出品":["極客影業有限公司","嘉映影業有限公司","霍爾果斯嘉美影業有限公司","上海極客文化傳播有限公司","上海尚世影業有限公司","亞博思文化傳媒有限公司","我們製作有限公司","阿里巴巴影業集團有限公司","天恩娛樂有限公司"],"上映院數":"7","銷售票數":"403","銷售金額":"88,890","金額變動率":"-65.31%","累計銷售票數":"24,078","累計銷售金額":"5,579,296","洲別":["亞洲"]},{"序號":50,"國別地區":["黎巴嫩"],"中文片名":"你只欠我一個道歉","上映日期":"2018/03/23","申請人":"海鵬影業有限公司","出品":["INDIE SALES CO"],"上映院數":"4","銷售票數":"378","銷售金額":"76,840","金額變動率":"-22.25%","累計銷售票數":"8,286","累計銷售金額":"1,760,610","洲別":["亞洲"]},{"序號":51,"國別地區":["美國"],"中文片名":"環太平洋2:起義時刻","上映日期":"2018/03/21","申請人":"美商美國環球影片股份有限公司台灣分公司","出品":["UNIVERSAL INTERNATIONAL FILMS LLC"],"上映院數":"46","銷售票數":"664","銷售金額":"156,760","金額變動率":"-89.77%","累計銷售票數":"704,973","累計銷售金額":"169,704,629","洲別":["北美洲"]},{"序號":52,"國別地區":["法國"],"中文片名":"極限登峰","上映日期":"2018/03/16","申請人":"亮點國際影業有限公司","出品":["GAUMONT S A"],"上映院數":"4","銷售票數":"157","銷售金額":"22,340","金額變動率":"0.00%","累計銷售票數":"1,346","累計銷售金額":"293,117","洲別":["歐洲"]},{"序號":53,"國別地區":["印度"],"中文片名":"人生起跑線","上映日期":"2018/03/16","申請人":"車庫娛樂股份有限公司","出品":["ATL MEDIA LTD"],"上映院數":"1","銷售票數":"23","銷售金額":"5,345","金額變動率":"-93.18%","累計銷售票數":"28,111","累計銷售金額":"6,304,909","洲別":["亞洲"]},{"序號":54,"國別地區":["西班牙"],"中文片名":"英勇勳章","上映日期":"2018/03/09","申請人":"峻龍國際有限公司","出品":["MULTIVISIONNAIRE INC"],"上映院數":"1","銷售票數":"40","銷售金額":"4,000","金額變動率":"0.00%","累計銷售票數":"2,061","累計銷售金額":"453,790","洲別":["歐洲"]},{"序號":55,"國別地區":["南韓"],"中文片名":"鬼搖靈","上映日期":"2018/03/09","申請人":"安可電影股份有限公司","出品":["CJ E & M CORPORATION"],"上映院數":"1","銷售票數":"16","銷售金額":"1,360","金額變動率":"-68.52%","累計銷售票數":"9,727","累計銷售金額":"2,233,147","洲別":["亞洲"]},{"序號":56,"國別地區":["美國"],"中文片名":"古墓奇兵","上映日期":"2018/03/08","申請人":"美商華納兄弟（遠東）股份有限公司台灣分公司","出品":["WARNER BROS PICTURES INTERNATIONAL"],"上映院數":"5","銷售票數":"92","銷售金額":"22,170","金額變動率":"-89.31%","累計銷售票數":"573,623","累計銷售金額":"136,650,954","洲別":["北美洲"]},{"序號":57,"國別地區":["美國"],"中文片名":"玩命颶風","上映日期":"2018/03/08","申請人":"香港商甲上娛樂有限公司台灣分公司","出品":["FORESIGHT UNLIMITED"],"上映院數":"1","銷售票數":"31","銷售金額":"6,820","金額變動率":"0.00%","累計銷售票數":"136,279","累計銷售金額":"31,452,817","洲別":["北美洲"]},{"序號":58,"國別地區":["日本"],"中文片名":"鎌倉物語","上映日期":"2018/03/02","申請人":"中影股份有限公司","出品":["NIPPON TELEVISION NETWORK CORPORATION"],"上映院數":"5","銷售票數":"494","銷售金額":"104,025","金額變動率":"-21.00%","累計銷售票數":"43,105","累計銷售金額":"9,600,570","洲別":["亞洲"]},{"序號":59,"國別地區":["香港"],"中文片名":"閨蜜2","上映日期":"2018/03/02","申請人":"華映娛樂股份有限公司","出品":["福建恒業影業有限公司","福建真恒業文化傳播有限公司","香港恒業影業有限公司","無限動力實業有限公司","中國數碼娛樂有限公司","完美星空傳媒有限公司","深圳市視界浪潮傳媒有限公司","中影新銳影業有限公司","重慶電影集團有限公司","北京新片場傳媒股份有限公司","揚州廣播電視總台"],"上映院數":"5","銷售票數":"422","銷售金額":"33,900","金額變動率":"0.00%","累計銷售票數":"121,932","累計銷售金額":"27,936,454","洲別":["亞洲"]},{"序號":60,"國別地區":["美國"],"中文片名":"對頭冤家","上映日期":"2018/03/02","申請人":"采昌國際多媒體股份有限公司","出品":["FILM & TV HOUSE LTD"],"上映院數":"3","銷售票數":"270","銷售金額":"19,330","金額變動率":"0.00%","累計銷售票數":"2,165","累計銷售金額":"454,486","洲別":["北美洲"]},{"序號":61,"國別地區":["美國"],"中文片名":"紅雀","上映日期":"2018/02/28","申請人":"美商廿世紀福斯影片股份有限公司台灣分公司","出品":["TWENTIETH CENTURY FOX INTERNATIONAL CORPORATION"],"上映院數":"6","銷售票數":"162","銷售金額":"37,220","金額變動率":"-87.49%","累計銷售票數":"728,574","累計銷售金額":"172,374,758","洲別":["北美洲"]},{"序號":62,"國別地區":["美國"],"中文片名":"遊戲夜殺必死","上映日期":"2018/02/27","申請人":"美商華納兄弟（遠東）股份有限公司台灣分公司","出品":["WARNER BROS PICTURES INTERNATIONAL"],"上映院數":"2","銷售票數":"56","銷售金額":"6,080","金額變動率":"0.00%","累計銷售票數":"85,491","累計銷售金額":"19,882,295","洲別":["北美洲"]},{"序號":63,"國別地區":["香港"],"中文片名":"西遊記女兒國","上映日期":"2018/02/15","申請人":"海樂影業股份有限公司","出品":["星皓影業有限公司","星皓影業有限公司"],"上映院數":"3","銷售票數":"220","銷售金額":"15,570","金額變動率":"-12.03%","累計銷售票數":"58,604","累計銷售金額":"12,975,741","洲別":["亞洲"]},{"序號":64,"國別地區":["美國"],"中文片名":"萌牛費迪南","上映日期":"2018/02/15","申請人":"美商廿世紀福斯影片股份有限公司台灣分公司","出品":["TWENTIETH CENTURY FOX INTERNATIONAL CORPORATION"],"上映院數":"2","銷售票數":"174","銷售金額":"14,180","金額變動率":"-23.60%","累計銷售票數":"124,219","累計銷售金額":"28,331,243","洲別":["北美洲"]},{"序號":65,"國別地區":["美國"],"中文片名":"黑豹","上映日期":"2018/02/13","申請人":"台灣華特迪士尼股份有限公司","出品":["BUENA VISTA INTERNATIONAL INC"],"上映院數":"1","銷售票數":"253","銷售金額":"65,450","金額變動率":"-32.03%","累計銷售票數":"1,558,318","累計銷售金額":"371,687,167","洲別":["北美洲"]},{"序號":66,"國別地區":["美國"],"中文片名":"意外","上映日期":"2018/02/09","申請人":"美商廿世紀福斯影片股份有限公司台灣分公司","出品":["TWENTIETH CENTURY FOX INTERNATIONAL CORPORATION"],"上映院數":"1","銷售票數":"2","銷售金額":"460","金額變動率":"-98.21%","累計銷售票數":"57,291","累計銷售金額":"12,894,077","洲別":["北美洲"]},{"序號":67,"國別地區":["美國"],"中文片名":"15:17巴黎列車","上映日期":"2018/02/08","申請人":"美商華納兄弟（遠東）股份有限公司台灣分公司","出品":["WARNER BROS PICTURES INTERNATIONAL"],"上映院數":"11","銷售票數":"1,109","銷售金額":"91,400","金額變動率":"26.16%","累計銷售票數":"70,400","累計銷售金額":"15,965,286","洲別":["北美洲"]},{"序號":68,"國別地區":["美國"],"中文片名":"金錢世界","上映日期":"2018/02/02","申請人":"英屬蓋曼群島商威望國際娛樂股份有限公司台灣分公司","出品":["STX PRODUCTIONS LLC"],"上映院數":"4","銷售票數":"411","銷售金額":"40,115","金額變動率":"1.05%","累計銷售票數":"44,504","累計銷售金額":"9,748,788","洲別":["北美洲"]},{"序號":69,"國別地區":["日本"],"中文片名":"電影版巧虎的彩虹綠洲","上映日期":"2018/02/02","申請人":"全民大劇團股份有限公司","出品":["倍樂生株式會社"],"上映院數":"10","銷售票數":"158","銷售金額":"38,599","金額變動率":"-13.53%","累計銷售票數":"42,212","累計銷售金額":"10,013,005","洲別":["亞洲"]},{"序號":70,"國別地區":["美國"],"中文片名":"溫徹斯特鬼屋","上映日期":"2018/02/02","申請人":"香港商甲上娛樂有限公司台灣分公司","出品":["ECLIPSE PICTURES INC"],"上映院數":"4","銷售票數":"237","銷售金額":"30,260","金額變動率":"14.32%","累計銷售票數":"113,784","累計銷售金額":"26,565,221","洲別":["北美洲"]},{"序號":71,"國別地區":["美國"],"中文片名":"霓裳魅影","上映日期":"2018/02/02","申請人":"美商美國環球影片股份有限公司台灣分公司","出品":["UNIVERSAL INTERNATIONAL FILMS LLC"],"上映院數":"4","銷售票數":"283","銷售金額":"17,300","金額變動率":"0.00%","累計銷售票數":"10,883","累計銷售金額":"2,385,082","洲別":["北美洲"]},{"序號":72,"國別地區":["美國"],"中文片名":"水底情深","上映日期":"2018/02/02","申請人":"美商廿世紀福斯影片股份有限公司台灣分公司","出品":["TWENTIETH CENTURY FOX INTERNATIONAL CORPORATION"],"上映院數":"3","銷售票數":"65","銷售金額":"7,390","金額變動率":"29.65%","累計銷售票數":"117,464","累計銷售金額":"27,810,864","洲別":["北美洲"]},{"序號":73,"國別地區":["美國"],"中文片名":"縮小人生","上映日期":"2018/01/26","申請人":"美商美國派拉蒙影片股份有限公司台灣分公司","出品":["PARAMOUNT PICTURES CORPORATION"],"上映院數":"12","銷售票數":"1,349","銷售金額":"104,360","金額變動率":"-35.55%","累計銷售票數":"144,764","累計銷售金額":"32,872,175","洲別":["北美洲"]},{"序號":74,"國別地區":["美國"],"中文片名":"老娘叫譚雅","上映日期":"2018/01/26","申請人":"海樂影業股份有限公司","出品":["FREEWAY ENTERTAINMENT KFT"],"上映院數":"6","銷售票數":"464","銷售金額":"52,635","金額變動率":"33.83%","累計銷售票數":"16,152","累計銷售金額":"3,412,013","洲別":["北美洲"]},{"序號":75,"國別地區":["美國"],"中文片名":"移動迷宮：死亡解藥","上映日期":"2018/01/19","申請人":"美商廿世紀福斯影片股份有限公司台灣分公司","出品":["TWENTIETH CENTURY FOX INTERNATIONAL CORPORATION"],"上映院數":"14","銷售票數":"2,728","銷售金額":"234,975","金額變動率":"24.46%","累計銷售票數":"762,465","累計銷售金額":"172,923,402","洲別":["北美洲"]},{"序號":76,"國別地區":["美國"],"中文片名":"大災難家","上映日期":"2018/01/19","申請人":"美商華納兄弟(遠東)股份有限公司台灣分公司","出品":["WARNER BROS PICTURES INTERNATIONAL"],"上映院數":"3","銷售票數":"125","銷售金額":"14,430","金額變動率":"12.82%","累計銷售票數":"39,871","累計銷售金額":"9,067,229","洲別":["北美洲"]},{"序號":77,"國別地區":["法國"],"中文片名":"疾速救援","上映日期":"2018/01/12","申請人":"英屬維京群島商高捷全球開發有限公司 台灣分公司","出品":["STUDIOCANAL"],"上映院數":"1","銷售票數":"164","銷售金額":"8,200","金額變動率":"-85.99%","累計銷售票數":"246,949","累計銷售金額":"56,860,489","洲別":["歐洲"]},{"序號":78,"國別地區":["英國"],"中文片名":"美國天使：重建（英國國家劇院現場）","上映日期":"2018/01/12","申請人":"威秀影城股份有限公司","出品":["THE ROYAL NATIONAL THEATRE"],"上映院數":"3","銷售票數":"8","銷售金額":"4,960","金額變動率":"-83.75%","累計銷售票數":"761","累計銷售金額":"508,520","洲別":["歐洲"]},{"序號":79,"國別地區":["英國"],"中文片名":"誰怕吳爾芙？（英國國家劇院現場）","上映日期":"2018/01/10","申請人":"威秀影城股份有限公司","出品":["THE ROYAL NATIONAL THEATRE"],"上映院數":"1","銷售票數":"44","銷售金額":"30,920","金額變動率":"0.00%","累計銷售票數":"576","累計銷售金額":"378,600","洲別":["歐洲"]},{"序號":80,"國別地區":["美國"],"中文片名":"最黑暗的時刻","上映日期":"2018/01/05","申請人":"美商美國環球影片股份有限公司台灣分公司","出品":["UNIVERSAL INTERNATIONAL FILMS LLC"],"上映院數":"9","銷售票數":"510","銷售金額":"52,860","金額變動率":"-40.46%","累計銷售票數":"37,346","累計銷售金額":"8,329,409","洲別":["北美洲"]},{"序號":81,"國別地區":["美國"],"中文片名":"陰兒房第4章：鎖命亡靈","上映日期":"2018/01/05","申請人":"博偉電影股份有限公司","出品":["SONY PICTURES RELEASING INTERNATIONAL CORPORATION"],"上映院數":"1","銷售票數":"82","銷售金額":"11,260","金額變動率":"21.08%","累計銷售票數":"140,678","累計銷售金額":"31,344,731","洲別":["北美洲"]},{"序號":82,"國別地區":["美國"],"中文片名":"野蠻遊戲：瘋狂叢林","上映日期":"2017/12/27","申請人":"博偉電影股份有限公司","出品":["SONY PICTURES RELEASING INTERNATIONAL CORPORATION"],"上映院數":"10","銷售票數":"1,217","銷售金額":"98,410","金額變動率":"-49.63%","累計銷售票數":"871,011","累計銷售金額":"202,595,935","洲別":["北美洲"]},{"序號":83,"國別地區":["美國"],"中文片名":"歌喉讚3","上映日期":"2017/12/27","申請人":"美商美國環球影片股份有限公司台灣分公司","出品":["UNIVERSAL INTERNATIONAL FILMS LLC"],"上映院數":"2","銷售票數":"122","銷售金額":"10,120","金額變動率":"-40.92%","累計銷售票數":"437,027","累計銷售金額":"100,440,667","洲別":["北美洲"]},{"序號":84,"國別地區":["美國"],"中文片名":"大娛樂家","上映日期":"2017/12/20","申請人":"美商廿世紀福斯影片股份有限公司台灣分公司","出品":["TWENTIETH CENTURY FOX INTERNATIONAL CORPORATION"],"上映院數":"8","銷售票數":"2,911","銷售金額":"217,230","金額變動率":"62.89%","累計銷售票數":"390,269","累計銷售金額":"91,480,372","洲別":["北美洲"]},{"序號":85,"國別地區":["法國"],"中文片名":"放牛班的提琴手","上映日期":"2017/12/08","申請人":"可樂藝術文創股份有限公司","出品":["GAUMONT S A"],"上映院數":"1","銷售票數":"27","銷售金額":"4,050","金額變動率":"-53.71%","累計銷售票數":"420","累計銷售金額":"81,170","洲別":["歐洲"]},{"序號":86,"國別地區":["美國"],"中文片名":"可可夜總會","上映日期":"2017/11/24","申請人":"台灣華特迪士尼股份有限公司","出品":["BUENA VISTA INTERNATIONAL INC"],"上映院數":"10","銷售票數":"1,684","銷售金額":"120,050","金額變動率":"-40.69%","累計銷售票數":"598,993","累計銷售金額":"135,112,942","洲別":["北美洲"]},{"序號":87,"國別地區":["法國"],"中文片名":"不思議女人","上映日期":"2017/11/24","申請人":"捷傑有限公司","出品":["FUNNY BALLOONS"],"上映院數":"1","銷售票數":"200","銷售金額":"38,000","金額變動率":"0.00%","累計銷售票數":"1,517","累計銷售金額":"321,366","洲別":["歐洲"]},{"序號":88,"國別地區":["日本"],"中文片名":"積存時間的生活","上映日期":"2017/11/10","申請人":"海鵬影業有限公司","出品":["BITTASTE INC"],"上映院數":"1","銷售票數":"84","銷售金額":"16,260","金額變動率":"-25.09%","累計銷售票數":"8,438","累計銷售金額":"1,813,984","洲別":["亞洲"]},{"序號":89,"國別地區":["美國"],"中文片名":"鋼鐵英雄","上映日期":"2016/11/25","申請人":"香港商甲上娛樂有限公司台灣分公司","出品":["IM GLOBAL LLC"],"上映院數":"1","銷售票數":"5","銷售金額":"860","金額變動率":"0.00%","累計銷售票數":"507,735","累計銷售金額":"115,709,426","洲別":["北美洲"]},{"序號":90,"國別地區":["美國"],"中文片名":"極地奇蹟-帶小北極熊回家","上映日期":"2016/01/22","申請人":"香港商甲上娛樂有限公司台灣分公司","出品":["POLAR ENTERTAINMENT INC"],"上映院數":"1","銷售票數":"2","銷售金額":"250","金額變動率":"0.00%","累計銷售票數":"7","累計銷售金額":"1,000","洲別":["北美洲"]},{"序號":91,"國別地區":["美國"],"中文片名":"玩具總動員3","上映日期":"2010/06/16","申請人":"台灣華特迪士尼股份有限公司","出品":["BUENA VISTA INTERNATIONAL INC"],"上映院數":"1","銷售票數":"78","銷售金額":"19,280","金額變動率":"50.86%","累計銷售票數":"451","累計銷售金額":"111,760","洲別":["北美洲"]},{"序號":92,"國別地區":["美國"],"中文片名":"玩具總動員","上映日期":"2010/06/16","申請人":"台灣華特迪士尼股份有限公司","出品":["BUENA VISTA INTERNATIONAL INC"],"上映院數":"1","銷售票數":"63","銷售金額":"15,750","金額變動率":"-0.51%","累計銷售票數":"274","累計銷售金額":"66,470","洲別":["北美洲"]},{"序號":93,"國別地區":["美國"],"中文片名":"玩具總動員2","上映日期":"2010/04/23","申請人":"台灣華特迪士尼股份有限公司","出品":["BUENA VISTA INTERNATIONAL INC"],"上映院數":"1","銷售票數":"53","銷售金額":"13,030","金額變動率":"6.63%","累計銷售票數":"270","累計銷售金額":"66,570","洲別":["北美洲"]}]