[{"序號":1,"國別地區":["法國"],"中文片名":"大鼻子情聖(經典劇場)","上映日期":"2020/02/01","申請人":"威秀影城股份有限公司","出品":["PATHÉ LIVE"],"上映院數":"4","銷售票數":"14","週票數變動率":"0.00%","銷售金額":"9,680","累計銷售票數":"14","累計銷售金額":"9,680","洲別":["歐洲"]},{"序號":2,"國別地區":["新加坡"],"中文片名":"熱帶雨","上映日期":"2020/01/31","申請人":"好威映象有限公司","出品":["GIRAFFE PICTURES PTE LTD"],"上映院數":"26","銷售票數":"1,862","週票數變動率":"-24.03%","銷售金額":"414,686","累計銷售票數":"4,313","累計銷售金額":"1,000,823","洲別":["亞洲"]},{"序號":3,"國別地區":["越南"],"中文片名":"鬼魅之家","上映日期":"2020/01/31","申請人":"水元素文化傳媒有限公司","出品":["SKYLINE MEDIA CO LTD"],"上映院數":"17","銷售票數":"1,651","週票數變動率":"-13.92%","銷售金額":"379,771","累計銷售票數":"3,569","累計銷售金額":"825,638","洲別":["亞洲"]},{"序號":4,"國別地區":["日本"],"中文片名":"王牌辯士","上映日期":"2020/01/31","申請人":"天馬行空數位有限公司","出品":["TOEI COMPANY LTD"],"上映院數":"15","銷售票數":"587","週票數變動率":"8.30%","銷售金額":"124,737","累計銷售票數":"1,129","累計銷售金額":"241,692","洲別":["亞洲"]},{"序號":5,"國別地區":["日本"],"中文片名":"只想受到你的歡迎","上映日期":"2020/01/31","申請人":"天馬行空數位有限公司","出品":["STARRY CUBE CORPORATION"],"上映院數":"7","銷售票數":"256","週票數變動率":"-19.75%","銷售金額":"62,930","累計銷售票數":"575","累計銷售金額":"140,325","洲別":["亞洲"]},{"序號":6,"國別地區":["日本"],"中文片名":"大整形家","上映日期":"2020/01/31","申請人":"原創娛樂股份有限公司","出品":["TOEI COMPANY LTD"],"上映院數":"6","銷售票數":"194","週票數變動率":"-19.50%","銷售金額":"44,075","累計銷售票數":"435","累計銷售金額":"101,470","洲別":["亞洲"]},{"序號":7,"國別地區":["日本"],"中文片名":"吸血黏土","上映日期":"2020/01/30","申請人":"暗光鳥有限公司","出品":["MONUMENT RELEASING LLC"],"上映院數":"5","銷售票數":"55","週票數變動率":"-32.93%","銷售金額":"11,520","累計銷售票數":"137","累計銷售金額":"29,296","洲別":["亞洲"]},{"序號":8,"國別地區":["美國"],"中文片名":"1917","上映日期":"2020/01/30","申請人":"美商美國環球影片股份有限公司台灣分公司","出品":["UNIVERSAL INTERNATIONAL FILMS LLC"],"上映院數":"99","銷售票數":"87,858","週票數變動率":"11.05%","銷售金額":"21,348,303","累計銷售票數":"166,977","累計銷售金額":"40,909,261","洲別":["北美洲"]},{"序號":9,"國別地區":["南韓"],"中文片名":"紅鞋公主與七矮人","上映日期":"2020/01/30","申請人":"可樂藝術文創股份有限公司","出品":["FINECUT CO LTD"],"上映院數":"44","銷售票數":"7,314","週票數變動率":"-13.52%","銷售金額":"1,690,822","累計銷售票數":"15,883","累計銷售金額":"3,674,938","洲別":["亞洲"]},{"序號":10,"國別地區":["美國"],"中文片名":"黑水風暴","上映日期":"2020/01/30","申請人":"車庫娛樂股份有限公司","出品":["STORYTELLER DISTRIBUTION CO LLC"],"上映院數":"49","銷售票數":"4,145","週票數變動率":"-27.99%","銷售金額":"950,549","累計銷售票數":"9,901","累計銷售金額":"2,290,359","洲別":["北美洲"]},{"序號":11,"國別地區":["美國"],"中文片名":"杜立德","上映日期":"2020/01/23","申請人":"美商美國環球影片股份有限公司台灣分公司","出品":["UNIVERSAL INTERNATIONAL FILMS LLC"],"上映院數":"100","銷售票數":"37,776","週票數變動率":"-73.28%","銷售金額":"8,867,550","累計銷售票數":"290,095","累計銷售金額":"69,800,705","洲別":["北美洲"]},{"序號":12,"國別地區":["美國"],"中文片名":"紳士追殺令","上映日期":"2020/01/23","申請人":"車庫娛樂股份有限公司","出品":["MIRAMAX DISTRIBUTION SERVICES LLC"],"上映院數":"63","銷售票數":"12,195","週票數變動率":"-72.04%","銷售金額":"2,921,382","累計銷售票數":"84,559","累計銷售金額":"20,301,783","洲別":["北美洲"]},{"序號":13,"國別地區":["香港"],"中文片名":"肥龍過江","上映日期":"2020/01/23","申請人":"華映娛樂股份有限公司","出品":["星王朝有限公司","上海博納文化傳媒有限公司","博納影業集團股份有限公司","上海新文化影業有限公司","電視廣播有限公司","太陽娛樂文化有限公司","上海杠杠影視文化有限公司","霍爾果斯環星影視傳媒有限公司","上海優創影視文化有限公司"],"上映院數":"93","銷售票數":"3,708","週票數變動率":"-86.91%","銷售金額":"813,588","累計銷售票數":"60,341","累計銷售金額":"13,373,472","洲別":["亞洲"]},{"序號":14,"國別地區":["中華民國"],"中文片名":"喜從天降","上映日期":"2020/01/23","申請人":"影一製作所股份有限公司","出品":["影一製作所股份有限公司"],"上映院數":"34","銷售票數":"421","週票數變動率":"-93.54%","銷售金額":"94,080","累計銷售票數":"15,970","累計銷售金額":"3,616,919","洲別":["亞洲"]},{"序號":15,"國別地區":["日本"],"中文片名":"我們的7日戰爭","上映日期":"2020/01/23","申請人":"海樂影業股份有限公司","出品":["KADOKAWA CORPORATION"],"上映院數":"15","銷售票數":"393","週票數變動率":"-80.93%","銷售金額":"91,735","累計銷售票數":"4,047","累計銷售金額":"959,918","洲別":["亞洲"]},{"序號":16,"國別地區":["中華民國"],"中文片名":"殺手撿到槍","上映日期":"2020/01/23","申請人":"星泰國際娛樂股份有限公司","出品":["滿滿額娛樂股份有限公司","華納集團"],"上映院數":"25","銷售票數":"369","週票數變動率":"-90.73%","銷售金額":"82,605","累計銷售票數":"9,359","累計銷售金額":"2,094,660","洲別":["亞洲"]},{"序號":17,"國別地區":["俄羅斯"],"中文片名":"岳父受死吧","上映日期":"2020/01/23","申請人":"麻吉砥加電影有限公司","出品":["REEL SUSPECTS S A R L"],"上映院數":"3","銷售票數":"9","週票數變動率":"-94.04%","銷售金額":"1,925","累計銷售票數":"291","累計銷售金額":"66,809","洲別":["亞洲"]},{"序號":18,"國別地區":["美國"],"中文片名":"變身特務","上映日期":"2020/01/22","申請人":"博偉電影股份有限公司","出品":["BUENA VISTA INTERNATIONAL INC"],"上映院數":"98","銷售票數":"19,659","週票數變動率":"-74.75%","銷售金額":"4,453,321","累計銷售票數":"167,411","累計銷售金額":"38,275,464","洲別":["北美洲"]},{"序號":19,"國別地區":["美國"],"中文片名":"深海終劫站","上映日期":"2020/01/22","申請人":"博偉電影股份有限公司","出品":["BUENA VISTA INTERNATIONAL INC"],"上映院數":"93","銷售票數":"19,140","週票數變動率":"-74.90%","銷售金額":"4,338,303","累計銷售票數":"167,027","累計銷售金額":"38,176,037","洲別":["北美洲"]},{"序號":20,"國別地區":["美國"],"中文片名":"她們","上映日期":"2020/01/22","申請人":"美商台灣索尼影業發行股份有限公司台灣分公司","出品":["SONY PICTURES RELEASING INTERNATIONAL CORPORATION"],"上映院數":"49","銷售票數":"15,665","週票數變動率":"-46.80%","銷售金額":"3,712,979","累計銷售票數":"67,126","累計銷售金額":"15,964,740","洲別":["北美洲"]},{"序號":21,"國別地區":["美國"],"中文片名":"不完美的正義","上映日期":"2020/01/17","申請人":"美商華納兄弟（遠東）股份有限公司台灣分公司","出品":["WARNER BROS PICTURES INTERNATIONAL"],"上映院數":"53","銷售票數":"1,487","週票數變動率":"-83.48%","銷售金額":"343,917","累計銷售票數":"46,147","累計銷售金額":"10,654,283","洲別":["北美洲"]},{"序號":22,"國別地區":["日本"],"中文片名":"巧虎電影 英雄遊樂園","上映日期":"2020/01/17","申請人":"全民大劇團股份有限公司","出品":["法人倍樂生株式會社"],"上映院數":"17","銷售票數":"1,087","週票數變動率":"-71.68%","銷售金額":"250,671","累計銷售票數":"16,283","累計銷售金額":"3,847,246","洲別":["亞洲"]},{"序號":23,"國別地區":["丹麥"],"中文片名":"在黑暗中漫舞：20週年數位修復版","上映日期":"2020/01/17","申請人":"光年映畫有限公司","出品":["TRUSTNORDISK APS"],"上映院數":"8","銷售票數":"320","週票數變動率":"-49.84%","銷售金額":"73,460","累計銷售票數":"4,339","累計銷售金額":"958,986","洲別":["歐洲"]},{"序號":24,"國別地區":["瑞典"],"中文片名":"然後我們跳了舞","上映日期":"2020/01/17","申請人":"海鵬影業有限公司","出品":["TOTEM FILMS SAS"],"上映院數":"5","銷售票數":"142","週票數變動率":"-67.05%","銷售金額":"31,225","累計銷售票數":"2,160","累計銷售金額":"457,255","洲別":["歐洲"]},{"序號":25,"國別地區":["南韓"],"中文片名":"青春催落去","上映日期":"2020/01/17","申請人":"車庫娛樂股份有限公司","出品":["CONTENTS PANDA"],"上映院數":"2","銷售票數":"23","週票數變動率":"-83.21%","銷售金額":"5,400","累計銷售票數":"5,027","累計銷售金額":"1,124,700","洲別":["亞洲"]},{"序號":26,"國別地區":["美國"],"中文片名":"絕地戰警FOR LIFE","上映日期":"2020/01/16","申請人":"美商台灣索尼影業發行股份有限公司台灣分公司","出品":["SONY PICTURES RELEASING INTERNATIONAL CORPORATION"],"上映院數":"98","銷售票數":"37,091","週票數變動率":"-73.99%","銷售金額":"8,773,439","累計銷售票數":"543,236","累計銷售金額":"129,956,225","洲別":["北美洲"]},{"序號":27,"國別地區":["中華民國"],"中文片名":"台北物語2-獲利者","上映日期":"2020/01/16","申請人":"丰采公關行銷有限公司","出品":["丰采公關行銷有限公司","健友國際企業有限公司"],"上映院數":"1","銷售票數":"63","週票數變動率":"152.00%","銷售金額":"14,040","累計銷售票數":"1,330","累計銷售金額":"305,165","洲別":["亞洲"]},{"序號":28,"國別地區":["加拿大"],"中文片名":"哥哥戀愛了，我怎麼辦!?","上映日期":"2020/01/15","申請人":"亮點國際影業有限公司","出品":["SEVILLE PICTURES INC"],"上映院數":"1","銷售票數":"3","週票數變動率":"-94.44%","銷售金額":"630","累計銷售票數":"608","累計銷售金額":"127,705","洲別":["北美洲"]},{"序號":29,"國別地區":["美國"],"中文片名":"重磅腥聞","上映日期":"2020/01/10","申請人":"車庫娛樂股份有限公司","出品":["LIONS GATE INTERNATIONAL LTD"],"上映院數":"20","銷售票數":"364","週票數變動率":"-75.07%","銷售金額":"81,926","累計銷售票數":"49,725","累計銷售金額":"11,582,593","洲別":["北美洲"]},{"序號":30,"國別地區":["日本"],"中文片名":"魯邦三世 THE FIRST","上映日期":"2020/01/10","申請人":"向洋影業有限公司","出品":["株式会社トムス・エンタテインメント"],"上映院數":"1","銷售票數":"51","週票數變動率":"-64.08%","銷售金額":"12,230","累計銷售票數":"13,337","累計銷售金額":"2,986,230","洲別":["亞洲"]},{"序號":31,"國別地區":["日本"],"中文片名":"動畫電影版 我想吃掉你的胰臟","上映日期":"2020/01/10","申請人":"車庫娛樂股份有限公司","出品":["ANIPLEX INC"],"上映院數":"1","銷售票數":"13","週票數變動率":"-75.93%","銷售金額":"3,400","累計銷售票數":"4,174","累計銷售金額":"1,009,066","洲別":["亞洲"]},{"序號":32,"國別地區":["美國"],"中文片名":"惡靈20","上映日期":"2020/01/10","申請人":"華映娛樂股份有限公司","出品":["HYDE PARK ENTERTAINMENT LLC"],"上映院數":"1","銷售票數":"2","週票數變動率":"-93.94%","銷售金額":"380","累計銷售票數":"4,823","累計銷售金額":"1,091,478","洲別":["北美洲"]},{"序號":33,"國別地區":["美國"],"中文片名":"兔嘲男孩","上映日期":"2020/01/03","申請人":"博偉電影股份有限公司","出品":["BUENA VISTA INTERNATIONAL INC"],"上映院數":"29","銷售票數":"1,940","週票數變動率":"-58.41%","銷售金額":"452,228","累計銷售票數":"86,374","累計銷售金額":"20,250,674","洲別":["北美洲"]},{"序號":34,"國別地區":["印度"],"中文片名":"真愛裁會贏","上映日期":"2020/01/03","申請人":"水元素文化傳媒有限公司","出品":["YASH RAJ FILMS PRIVATE LTD"],"上映院數":"2","銷售票數":"20","週票數變動率":"-92.00%","銷售金額":"4,140","累計銷售票數":"5,972","累計銷售金額":"1,260,791","洲別":["亞洲"]},{"序號":35,"國別地區":["中華民國"],"中文片名":"你的情歌","上映日期":"2020/01/02","申請人":"香港商甲上娛樂有限公司台灣分公司","出品":["奇想事企業有限公司","能率影業股份有限公司","香港商甲上娛樂有限公司台灣分公司","采昌國際多媒體股份有限公司","英屬維京群島商敦宜股份有限公司台灣分公司"],"上映院數":"67","銷售票數":"17,141","週票數變動率":"-42.12%","銷售金額":"3,994,406","累計銷售票數":"61,590","累計銷售金額":"14,470,784","洲別":["亞洲"]},{"序號":36,"國別地區":["英國"],"中文片名":"國王與我","上映日期":"2020/01/01","申請人":"威秀影城股份有限公司","出品":["TRAFALGAR RELEASING LTD"],"上映院數":"2","銷售票數":"47","週票數變動率":"0.00%","銷售金額":"34,640","累計銷售票數":"218","累計銷售金額":"156,760","洲別":["歐洲"]},{"序號":37,"國別地區":["美國"],"中文片名":"倒數計死","上映日期":"2019/12/27","申請人":"采昌國際多媒體股份有限公司","出品":["STX PRODUCTIONS LLC"],"上映院數":"6","銷售票數":"271","週票數變動率":"-74.53%","銷售金額":"56,660","累計銷售票數":"72,602","累計銷售金額":"16,586,141","洲別":["北美洲"]},{"序號":38,"國別地區":["中國大陸"],"中文片名":"吹哨人","上映日期":"2019/12/27","申請人":"內容物數位電影製作有限公司","出品":["華文映像影業有限公司","珠海市洲際金瑪文化有限公司","北京和禾和文化傳媒有限責任公司","浙江火麥影視傳媒有限公司","中英電影文化基金有限公司","天津貓眼微影文化傳媒有限公司","溫和巨人媒體集團","天津十間影視傳媒有限公司","騰訊影業文化傳播有限公司","完美威秀娛樂有限公司","安樂影片有限公司","北京佳文映畫文化傳媒有限責任公司","墨客行影業有限公司","耳東文化有限公司"],"上映院數":"1","銷售票數":"24","週票數變動率":"0.00%","銷售金額":"3,840","累計銷售票數":"2,182","累計銷售金額":"471,101","洲別":["亞洲"]},{"序號":39,"國別地區":["法國"],"中文片名":"潛艦追緝","上映日期":"2019/12/27","申請人":"鴻聯國際開發股份有限公司","出品":["PATHE FILMS S A S"],"上映院數":"1","銷售票數":"24","週票數變動率":"26.32%","銷售金額":"3,120","累計銷售票數":"9,679","累計銷售金額":"2,125,577","洲別":["歐洲"]},{"序號":40,"國別地區":["美國"],"中文片名":"霹靂嬌娃","上映日期":"2019/12/27","申請人":"美商台灣索尼影業發行股份有限公司台灣分公司","出品":["SONY PICTURES RELEASING INTERNATIONAL CORPORATION"],"上映院數":"3","銷售票數":"8","週票數變動率":"-96.61%","銷售金額":"1,770","累計銷售票數":"124,727","累計銷售金額":"28,535,409","洲別":["北美洲"]},{"序號":41,"國別地區":["南韓"],"中文片名":"白頭山：半島浩劫","上映日期":"2019/12/24","申請人":"車庫娛樂股份有限公司","出品":["CJ ENM CO LTD"],"上映院數":"38","銷售票數":"2,186","週票數變動率":"-84.56%","銷售金額":"521,736","累計銷售票數":"497,817","累計銷售金額":"115,633,055","洲別":["亞洲"]},{"序號":42,"國別地區":["法國"],"中文片名":"燃燒女子的畫像","上映日期":"2019/12/20","申請人":"東昊影業有限公司","出品":["MK2 FILMS"],"上映院數":"6","銷售票數":"432","週票數變動率":"-28.48%","銷售金額":"94,940","累計銷售票數":"14,204","累計銷售金額":"3,134,923","洲別":["歐洲"]},{"序號":43,"國別地區":["香港"],"中文片名":"葉問4：完結篇","上映日期":"2019/12/19","申請人":"華映娛樂股份有限公司","出品":["東方影業出品有限公司"],"上映院數":"40","銷售票數":"1,011","週票數變動率":"-85.90%","銷售金額":"244,762","累計銷售票數":"806,294","累計銷售金額":"185,081,448","洲別":["亞洲"]},{"序號":44,"國別地區":["美國"],"中文片名":"STAR WARS : 天行者的崛起","上映日期":"2019/12/18","申請人":"台灣華特迪士尼股份有限公司","出品":["BUENA VISTA INTERNATIONAL INC"],"上映院數":"2","銷售票數":"46","週票數變動率":"-84.72%","銷售金額":"12,275","累計銷售票數":"324,331","累計銷售金額":"82,150,239","洲別":["北美洲"]},{"序號":45,"國別地區":["中華民國"],"中文片名":"黑熊來了","上映日期":"2019/12/13","申請人":"牽猴子整合行銷股份有限公司","出品":["大麥影像傳播工作室"],"上映院數":"7","銷售票數":"157","週票數變動率":"-74.26%","銷售金額":"36,460","累計銷售票數":"51,427","累計銷售金額":"11,725,230","洲別":["亞洲"]},{"序號":46,"國別地區":["美國"],"中文片名":"大說謊家","上映日期":"2019/12/13","申請人":"美商華納兄弟（遠東）股份有限公司台灣分公司","出品":["WARNER BROS PICTURES INTERNATIONAL"],"上映院數":"4","銷售票數":"357","週票數變動率":"0.00%","銷售金額":"23,790","累計銷售票數":"35,291","累計銷售金額":"8,000,270","洲別":["北美洲"]},{"序號":47,"國別地區":["南韓"],"中文片名":"黑計畫","上映日期":"2019/12/13","申請人":"英屬蓋曼群島商威望國際娛樂股份有限公司台灣分公司","出品":["CONTENTS PANDA"],"上映院數":"2","銷售票數":"118","週票數變動率":"0.00%","銷售金額":"8,800","累計銷售票數":"4,636","累計銷售金額":"1,038,915","洲別":["亞洲"]},{"序號":48,"國別地區":["法國"],"中文片名":"巴黎小情聖","上映日期":"2019/12/13","申請人":"鴻聯國際開發股份有限公司","出品":["GAUMONT"],"上映院數":"1","銷售票數":"2","週票數變動率":"-86.67%","銷售金額":"400","累計銷售票數":"985","累計銷售金額":"202,860","洲別":["歐洲"]},{"序號":49,"國別地區":["英國"],"中文片名":"給我一個參選的理由","上映日期":"2019/12/11","申請人":"威秀影城股份有限公司","出品":["THE ROYAL NATIONAL THEATRE"],"上映院數":"1","銷售票數":"70","週票數變動率":"0.00%","銷售金額":"44,500","累計銷售票數":"303","累計銷售金額":"193,580","洲別":["歐洲"]},{"序號":50,"國別地區":["英國"],"中文片名":"茱蒂","上映日期":"2019/12/10","申請人":"采昌國際多媒體股份有限公司","出品":["PATHE FUND LIMITED THROUGH DIVISION PATHE INTERNATIONAL"],"上映院數":"12","銷售票數":"260","週票數變動率":"45.25%","銷售金額":"61,804","累計銷售票數":"11,020","累計銷售金額":"2,431,287","洲別":["歐洲"]},{"序號":51,"國別地區":["日本"],"中文片名":"特約經紀公司","上映日期":"2019/12/06","申請人":"華映娛樂股份有限公司","出品":["SHOCHIKU CO LTD"],"上映院數":"1","銷售票數":"38","週票數變動率":"46.15%","銷售金額":"5,780","累計銷售票數":"7,174","累計銷售金額":"1,600,880","洲別":["亞洲"]},{"序號":52,"國別地區":["美國"],"中文片名":"野蠻遊戲：全面晉級","上映日期":"2019/12/04","申請人":"美商台灣索尼影業發行股份有限公司台灣分公司","出品":["SONY PICTURES RELEASING INTERNATIONAL CORPORATION"],"上映院數":"12","銷售票數":"357","週票數變動率":"-85.89%","銷售金額":"89,470","累計銷售票數":"806,110","累計銷售金額":"190,009,570","洲別":["北美洲"]},{"序號":53,"國別地區":["英國"],"中文片名":"哈利路亞！","上映日期":"2019/12/04","申請人":"威秀影城股份有限公司","出品":["THE ROYAL NATIONAL THEATRE"],"上映院數":"2","銷售票數":"58","週票數變動率":"0.00%","銷售金額":"35,800","累計銷售票數":"248","累計銷售金額":"155,440","洲別":["歐洲"]},{"序號":54,"國別地區":["英國"],"中文片名":"茱莉小姐","上映日期":"2019/12/04","申請人":"威秀影城股份有限公司","出品":["THE ROYAL NATIONAL THEATRE"],"上映院數":"3","銷售票數":"29","週票數變動率":"-62.34%","銷售金額":"19,800","累計銷售票數":"289","累計銷售金額":"188,060","洲別":["歐洲"]},{"序號":55,"國別地區":["美國"],"中文片名":"暴走曼哈頓","上映日期":"2019/11/29","申請人":"英屬蓋曼群島商威望國際娛樂股份有限公司台灣分公司","出品":["STX PRODUCTIONS LLC"],"上映院數":"5","銷售票數":"254","週票數變動率":"-18.85%","銷售金額":"28,760","累計銷售票數":"32,511","累計銷售金額":"7,130,448","洲別":["北美洲"]},{"序號":56,"國別地區":["美國"],"中文片名":"布魯克林孤兒","上映日期":"2019/11/29","申請人":"美商華納兄弟（遠東）股份有限公司台灣分公司","出品":["WARNER BROS PICTURES INTERNATIONAL"],"上映院數":"4","銷售票數":"255","週票數變動率":"40.88%","銷售金額":"25,255","累計銷售票數":"21,312","累計銷售金額":"4,722,709","洲別":["北美洲"]},{"序號":57,"國別地區":["丹麥"],"中文片名":"懸案密碼前傳-瓶中信","上映日期":"2019/11/29","申請人":"峻龍國際有限公司","出品":["MULTIVISIONNAIRE INC"],"上映院數":"1","銷售票數":"32","週票數變動率":"68.42%","銷售金額":"5,120","累計銷售票數":"5,438","累計銷售金額":"1,170,589","洲別":["歐洲"]},{"序號":58,"國別地區":["美國"],"中文片名":"鋒迴路轉","上映日期":"2019/11/28","申請人":"車庫娛樂股份有限公司","出品":["LIONS GATE INTERNATIONAL LTD"],"上映院數":"1","銷售票數":"8","週票數變動率":"-94.16%","銷售金額":"1,730","累計銷售票數":"165,790","累計銷售金額":"38,494,724","洲別":["北美洲"]},{"序號":59,"國別地區":["美國"],"中文片名":"賽道狂人","上映日期":"2019/11/26","申請人":"博偉電影股份有限公司","出品":["BUENA VISTA INTERNATIONAL INC"],"上映院數":"4","銷售票數":"62","週票數變動率":"-82.08%","銷售金額":"15,425","累計銷售票數":"314,157","累計銷售金額":"77,347,893","洲別":["北美洲"]},{"序號":60,"國別地區":["南韓"],"中文片名":"82年生的金智英","上映日期":"2019/11/22","申請人":"車庫娛樂股份有限公司","出品":["LOTTE CULTUREWORKS CO LTD"],"上映院數":"1","銷售票數":"2","週票數變動率":"-60.00%","銷售金額":"510","累計銷售票數":"138,398","累計銷售金額":"32,474,962","洲別":["亞洲"]},{"序號":61,"國別地區":["美國"],"中文片名":"冰雪奇緣2","上映日期":"2019/11/21","申請人":"台灣華特迪士尼股份有限公司","出品":["BUENA VISTA INTERNATIONAL INC"],"上映院數":"23","銷售票數":"848","週票數變動率":"-78.97%","銷售金額":"199,754","累計銷售票數":"1,449,532","累計銷售金額":"343,420,673","洲別":["北美洲"]},{"序號":62,"國別地區":["印度"],"中文片名":"萬萬沒想到","上映日期":"2019/11/15","申請人":"英屬蓋曼群島商威望國際娛樂股份有限公司台灣分公司","出品":["STAR INDIA PRIVATE LIMITED THROUGH DIVISION FOX STAR STUDIOS"],"上映院數":"7","銷售票數":"660","週票數變動率":"185.71%","銷售金額":"46,535","累計銷售票數":"48,874","累計銷售金額":"10,960,439","洲別":["亞洲"]},{"序號":63,"國別地區":["美國"],"中文片名":"決戰中途島","上映日期":"2019/11/08","申請人":"台北双喜電影發行股份有限公司","出品":["BONA FILM INVESTMENT CO"],"上映院數":"9","銷售票數":"1,512","週票數變動率":"-24.44%","銷售金額":"134,270","累計銷售票數":"317,984","累計銷售金額":"72,803,561","洲別":["北美洲"]},{"序號":64,"國別地區":["美國"],"中文片名":"安眠醫生","上映日期":"2019/11/08","申請人":"美商華納兄弟（遠東）股份有限公司台灣分公司","出品":["WARNER BROS PICTURES INTERNATIONAL"],"上映院數":"5","銷售票數":"422","週票數變動率":"-24.51%","銷售金額":"46,660","累計銷售票數":"125,235","累計銷售金額":"29,625,149","洲別":["北美洲"]},{"序號":65,"國別地區":["美國"],"中文片名":"救火奶爸","上映日期":"2019/11/08","申請人":"美商美國派拉蒙影片股份有限公司台灣分公司","出品":["PARAMOUNT PICTURES CORPORATION"],"上映院數":"7","銷售票數":"537","週票數變動率":"20.95%","銷售金額":"44,905","累計銷售票數":"20,655","累計銷售金額":"4,547,982","洲別":["北美洲"]},{"序號":66,"國別地區":["美國"],"中文片名":"魔鬼終結者：黑暗宿命","上映日期":"2019/11/07","申請人":"博偉電影股份有限公司","出品":["BUENA VISTA INTERNATIONAL INC"],"上映院數":"9","銷售票數":"921","週票數變動率":"-64.40%","銷售金額":"74,075","累計銷售票數":"379,296","累計銷售金額":"88,102,704","洲別":["北美洲"]},{"序號":67,"國別地區":["美國"],"中文片名":"絕鯊47：猛鯊出籠","上映日期":"2019/11/01","申請人":"車庫娛樂股份有限公司","出品":["GEM ENTERTAINMENT KFT"],"上映院數":"5","銷售票數":"413","週票數變動率":"0.00%","銷售金額":"31,330","累計銷售票數":"26,839","累計銷售金額":"5,858,590","洲別":["北美洲"]},{"序號":68,"國別地區":["美國"],"中文片名":"阿達一族","上映日期":"2019/11/01","申請人":"美商美國環球影片股份有限公司台灣分公司","出品":["PARK CIRCUS LTD"],"上映院數":"2","銷售票數":"161","週票數變動率":"-74.40%","銷售金額":"11,690","累計銷售票數":"89,368","累計銷售金額":"20,199,885","洲別":["北美洲"]},{"序號":69,"國別地區":["中華民國"],"中文片名":"傻傻愛你，傻傻愛我","上映日期":"2019/11/01","申請人":"華映娛樂股份有限公司","出品":["華映娛樂股份有限公司","講故事有限公司","中環國際娛樂事業股份有限公司","星泰國際娛樂股份有限公司","樂到家國際娛樂股份有限公司","艾迪昇傳播事業有限公司","滿滿額娛樂股份有限公司","天際娛樂股份有限公司","劇龍製作有限公司"],"上映院數":"1","銷售票數":"12","週票數變動率":"-77.78%","銷售金額":"1,680","累計銷售票數":"42,296","累計銷售金額":"9,477,447","洲別":["亞洲"]},{"序號":70,"國別地區":["美國"],"中文片名":"雙子殺手","上映日期":"2019/10/23","申請人":"美商美國派拉蒙影片股份有限公司台灣分公司","出品":["PARAMOUNT PICTURES CORPORATION"],"上映院數":"3","銷售票數":"477","週票數變動率":"-47.47%","銷售金額":"27,610","累計銷售票數":"552,660","累計銷售金額":"132,765,426","洲別":["北美洲"]},{"序號":71,"國別地區":["中華民國"],"中文片名":"盲人律師","上映日期":"2019/10/18","申請人":"春暉映像有限公司","出品":["牧風電影事業有限合夥"],"上映院數":"2","銷售票數":"42","週票數變動率":"600.00%","銷售金額":"11,010","累計銷售票數":"28,385","累計銷售金額":"6,215,086","洲別":["亞洲"]},{"序號":72,"國別地區":["日本"],"中文片名":"七個會議","上映日期":"2019/10/18","申請人":"鴻聯國際開發股份有限公司","出品":["TOKYO BROADCASTING SYSTEM TELEVISION INC"],"上映院數":"1","銷售票數":"24","週票數變動率":"0.00%","銷售金額":"3,840","累計銷售票數":"5,183","累計銷售金額":"1,131,362","洲別":["亞洲"]},{"序號":73,"國別地區":["南韓"],"中文片名":"加油吧 ! 李先生","上映日期":"2019/10/18","申請人":"車庫娛樂股份有限公司","出品":["CONTENTS PANDA"],"上映院數":"1","銷售票數":"16","週票數變動率":"-77.14%","銷售金額":"2,240","累計銷售票數":"3,360","累計銷售金額":"741,987","洲別":["亞洲"]},{"序號":74,"國別地區":["美國"],"中文片名":"黑魔女2","上映日期":"2019/10/17","申請人":"台灣華特迪士尼股份有限公司","出品":["BUENA VISTA INTERNATIONAL INC"],"上映院數":"8","銷售票數":"1,027","週票數變動率":"-41.98%","銷售金額":"91,435","累計銷售票數":"589,257","累計銷售金額":"137,737,736","洲別":["北美洲"]},{"序號":75,"國別地區":["中華民國"],"中文片名":"江湖無難事","上映日期":"2019/10/09","申請人":"鹿路電影有限公司","出品":["上海愛美影視文化傳媒有限公司","滿滿額娛樂股份有限公司","華映娛樂股份有限公司","內容物數位電影製作有限公司","高雄人","鹿路電影有限公司","發條映画有限公司","百聿數碼創意股份有限公司"],"上映院數":"1","銷售票數":"25","週票數變動率":"0.00%","銷售金額":"2,420","累計銷售票數":"42,566","累計銷售金額":"9,225,468","洲別":["亞洲"]},{"序號":76,"國別地區":["美國"],"中文片名":"小丑","上映日期":"2019/10/03","申請人":"美商華納兄弟（遠東）股份有限公司台灣分公司","出品":["WARNER BROS PICTURES INTERNATIONAL"],"上映院數":"18","銷售票數":"532","週票數變動率":"254.67%","銷售金額":"133,765","累計銷售票數":"1,389,255","累計銷售金額":"331,325,515","洲別":["北美洲"]},{"序號":77,"國別地區":["美國"],"中文片名":"囧媽的極地任務","上映日期":"2019/09/27","申請人":"車庫娛樂股份有限公司","出品":["METRO-GOLDWYN-MAYER STUDIOS INC"],"上映院數":"2","銷售票數":"108","週票數變動率":"-64.00%","銷售金額":"5,745","累計銷售票數":"11,904","累計銷售金額":"2,408,421","洲別":["北美洲"]},{"序號":78,"國別地區":["英國"],"中文片名":"無間行動","上映日期":"2019/09/27","申請人":"星泰國際娛樂股份有限公司","出品":["BATRAX ENTERTAINMENT"],"上映院數":"1","銷售票數":"54","週票數變動率":"-65.82%","銷售金額":"2,970","累計銷售票數":"36,369","累計銷售金額":"7,823,942","洲別":["歐洲"]},{"序號":79,"國別地區":["日本"],"中文片名":"信用詐欺師JP","上映日期":"2019/09/27","申請人":"傳影互動股份有限公司","出品":["PONY CANYON INC"],"上映院數":"1","銷售票數":"19","週票數變動率":"-67.24%","銷售金額":"2,660","累計銷售票數":"15,573","累計銷售金額":"3,560,507","洲別":["亞洲"]},{"序號":80,"國別地區":["中華民國"],"中文片名":"返校","上映日期":"2019/09/20","申請人":"影一製作所股份有限公司","出品":["影一製作所股份有限公司","遊戲橘子數位科技股份有限公司","英屬維京群島商敦宜股份有限公司台灣分公司","樂到家國際娛樂股份有限公司","一條龍虎豹國際娛樂有限公司","財團法人臺中市影視發展基金會","高雄市電影館","美商華納兄弟股份有限公司台灣分公司"],"上映院數":"3","銷售票數":"246","週票數變動率":"-71.43%","銷售金額":"14,190","累計銷售票數":"1,120,671","累計銷售金額":"260,442,080","洲別":["亞洲"]},{"序號":81,"國別地區":["日本"],"中文片名":"殺手餐廳","上映日期":"2019/09/20","申請人":"天馬行空數位有限公司","出品":["NIPPON TELEVISION NETWORK CORPORATION"],"上映院數":"1","銷售票數":"4","週票數變動率":"0.00%","銷售金額":"1,020","累計銷售票數":"5,021","累計銷售金額":"1,194,513","洲別":["亞洲"]},{"序號":82,"國別地區":["日本"],"中文片名":"天氣之子","上映日期":"2019/09/12","申請人":"車庫娛樂股份有限公司","出品":["TOHO CO LTD"],"上映院數":"10","銷售票數":"1,365","週票數變動率":"-52.75%","銷售金額":"108,765","累計銷售票數":"691,476","累計銷售金額":"165,352,565","洲別":["亞洲"]},{"序號":83,"國別地區":["日本"],"中文片名":"普羅米亞","上映日期":"2019/08/16","申請人":"中影股份有限公司","出品":["東寶株式會社"],"上映院數":"1","銷售票數":"112","週票數變動率":"0.00%","銷售金額":"26,880","累計銷售票數":"76,335","累計銷售金額":"21,170,540","洲別":["亞洲"]},{"序號":84,"國別地區":["美國"],"中文片名":"仙戒奇緣","上映日期":"2019/08/16","申請人":"可樂藝術文創股份有限公司","出品":["GOLD VALLEY FILMS INC"],"上映院數":"1","銷售票數":"98","週票數變動率":"-70.03%","銷售金額":"4,900","累計銷售票數":"6,635","累計銷售金額":"1,365,465","洲別":["北美洲"]},{"序號":85,"國別地區":["西班牙"],"中文片名":"痛苦與榮耀","上映日期":"2019/08/02","申請人":"傳影互動股份有限公司","出品":["BATRAX ENTERTAINMENT B V"],"上映院數":"1","銷售票數":"30","週票數變動率":"-42.31%","銷售金額":"6,120","累計銷售票數":"14,650","累計銷售金額":"2,985,122","洲別":["歐洲"]},{"序號":86,"國別地區":["美國"],"中文片名":"從前，有個好萊塢","上映日期":"2019/07/24","申請人":"台北双喜電影發行股份有限公司","出品":["BONA FILM INVESTMENT CO"],"上映院數":"12","銷售票數":"128","週票數變動率":"-3.76%","銷售金額":"30,807","累計銷售票數":"157,726","累計銷售金額":"37,621,731","洲別":["北美洲"]},{"序號":87,"國別地區":["南韓"],"中文片名":"寄生上流","上映日期":"2019/06/28","申請人":"英屬蓋曼群島商威望國際娛樂股份有限公司台灣分公司","出品":["CJ ENM CO LTD"],"上映院數":"19","銷售票數":"657","週票數變動率":"-23.87%","銷售金額":"158,398","累計銷售票數":"629,945","累計銷售金額":"146,857,428","洲別":["亞洲"]},{"序號":88,"國別地區":["西班牙"],"中文片名":"騙局","上映日期":"2019/03/22","申請人":"海鵬影業有限公司","出品":["LATIDO CONSORCIO DE EXPORTACION DEL CINE ESPANOL SL"],"上映院數":"1","銷售票數":"2","週票數變動率":"0.00%","銷售金額":"250","累計銷售票數":"6,403","累計銷售金額":"1,429,688","洲別":["歐洲"]},{"序號":89,"國別地區":["加拿大"],"中文片名":"哈柏太空之旅 3D","上映日期":"2019/02/04","申請人":"國際電影事業有限公司","出品":["IMAX CORPORATION"],"上映院數":"1","銷售票數":"2","週票數變動率":"-77.78%","銷售金額":"660","累計銷售票數":"589","累計銷售金額":"84,675","洲別":["北美洲"]},{"序號":90,"國別地區":["加拿大"],"中文片名":"深海獵奇 3D","上映日期":"2019/02/03","申請人":"國際電影事業有限公司","出品":["IMAX CORPORATION"],"上映院數":"1","銷售票數":"0","週票數變動率":"0.00%","銷售金額":"0","累計銷售票數":"1,189","累計銷售金額":"147,889","洲別":["北美洲"]},{"序號":91,"國別地區":["法國"],"中文片名":"巴黎交易員","上映日期":"2017/05/12","申請人":"海鵬影業有限公司","出品":["LE PACTE"],"上映院數":"1","銷售票數":"3","週票數變動率":"0.00%","銷售金額":"440","累計銷售票數":"3,972","累計銷售金額":"899,445","洲別":["歐洲"]},{"序號":92,"國別地區":["法國"],"中文片名":"巴黎野玫瑰","上映日期":"2016/05/27","申請人":"南強國際影視傳播有限公司","出品":["LE PETIT BUREAU"],"上映院數":"1","銷售票數":"1","週票數變動率":"-90.00%","銷售金額":"150","累計銷售票數":"2,787","累計銷售金額":"630,035","洲別":["歐洲"]},{"序號":93,"國別地區":["義大利"],"中文片名":"海上鋼琴師","上映日期":"1998/01/01","申請人":"海鵬影業有限公司","出品":["TRUE COLOURS GLORIOUS FILMS SRL"],"上映院數":"4","銷售票數":"157","週票數變動率":"-64.64%","銷售金額":"34,930","累計銷售票數":"17,019","累計銷售金額":"3,855,888","洲別":["歐洲"]}]