[{"序號":1,"國別地區":["美國"],"中文片名":"路卡的夏天","上映日期":"2021/08/06","申請人":"台灣華特迪士尼股份有限公司","出品":["BUENA VISTA INTERNATIONAL INC"],"上映院數":87,"銷售票數":13706,"週票數變動率":0.6515,"銷售金額":3350058,"累計銷售票數":22005,"累計銷售金額":5400442,"洲別":["北美洲"]},{"序號":2,"國別地區":["日本"],"中文片名":"甲子園：夢想競技場","上映日期":"2021/08/06","申請人":"佳映娛樂國際股份有限公司","出品":["NIKKATSU CORPORATION"],"上映院數":2,"銷售票數":68,"週票數變動率":3.5333,"銷售金額":13910,"累計銷售票數":83,"累計銷售金額":16665,"洲別":["亞洲"]},{"序號":3,"國別地區":["日本"],"中文片名":"青春：第50屆日本全國高中棒球錦標賽","上映日期":"2021/08/06","申請人":"佳映娛樂國際股份有限公司","出品":["NIKKATSU CORPORATION"],"上映院數":2,"銷售票數":28,"週票數變動率":3.6667,"銷售金額":5735,"累計銷售票數":34,"累計銷售金額":6835,"洲別":["亞洲"]},{"序號":4,"國別地區":["南韓"],"中文片名":"妻子的101次結婚","上映日期":"2021/08/06","申請人":"英屬維京群島商映畫聯合有限公司台灣分公司","出品":["STUDIO BONANZA INC"],"上映院數":3,"銷售票數":5,"週票數變動率":-0.5833,"銷售金額":1260,"累計銷售票數":17,"累計銷售金額":4245,"洲別":["亞洲"]},{"序號":5,"國別地區":["中國大陸"],"中文片名":"合法伴侶","上映日期":"2021/08/06","申請人":"秀泰國際娛樂有限公司","出品":["上海尚世影業有限公司","上海三次元影業有限公司","天津貓眼微影文化傳媒有限公司","英國澤風影業","杭州蝸牛投資管理有限公司","北京樂波影業有限公司","英皇影視文化傳媒有限公司","英皇影業有限公司"],"上映院數":2,"銷售票數":7,"週票數變動率":-0.3,"銷售金額":1250,"累計銷售票數":17,"累計銷售金額":3470,"洲別":["亞洲"]},{"序號":6,"國別地區":["美國"],"中文片名":"自殺突擊隊：集結","上映日期":"2021/08/05","申請人":"美商華納兄弟（遠東）股份有限公司台灣分公司","出品":["WARNER BROS PICTURES INTERNATIONAL"],"上映院數":96,"銷售票數":79528,"週票數變動率":0.3681,"銷售金額":20183012,"累計銷售票數":137657,"累計銷售金額":35404345,"洲別":["北美洲"]},{"序號":7,"國別地區":["美國"],"中文片名":"驅魔禁區","上映日期":"2021/08/05","申請人":"車庫娛樂股份有限公司","出品":["RELAY MOTION KFT"],"上映院數":45,"銷售票數":865,"週票數變動率":-0.1128,"銷售金額":217814,"累計銷售票數":1840,"累計銷售金額":462142,"洲別":["北美洲"]},{"序號":8,"國別地區":["南韓"],"中文片名":"BLACKPINK THE MOVIE","上映日期":"2021/08/04","申請人":"威秀影城股份有限公司","出品":["CJ 4DPLEX CO LTD"],"上映院數":12,"銷售票數":860,"週票數變動率":-0.6098,"銷售金額":404400,"累計銷售票數":3064,"累計銷售金額":1448760,"洲別":["亞洲"]},{"序號":9,"國別地區":["美國"],"中文片名":"叢林奇航","上映日期":"2021/07/30","申請人":"台灣華特迪士尼股份有限公司","出品":["BUENA VISTA INTERNATIONAL INC"],"上映院數":94,"銷售票數":11024,"週票數變動率":-0.54,"銷售金額":2710898,"累計銷售票數":56460,"累計銷售金額":14181603,"洲別":["北美洲"]},{"序號":10,"國別地區":["美國"],"中文片名":"詭老","上映日期":"2021/07/30","申請人":"美商美國環球影片股份有限公司台灣分公司","出品":["UNIVERSAL INTERNATIONAL FILMS LLC"],"上映院數":87,"銷售票數":2865,"週票數變動率":-0.5807,"銷售金額":716218,"累計銷售票數":14570,"累計銷售金額":3596155,"洲別":["北美洲"]},{"序號":11,"國別地區":["南韓"],"中文片名":"怪奇大廈","上映日期":"2021/07/30","申請人":"車庫娛樂股份有限公司","出品":["RELAY MOTION KFT"],"上映院數":25,"銷售票數":216,"週票數變動率":-0.8242,"銷售金額":53936,"累計銷售票數":2380,"累計銷售金額":591185,"洲別":["亞洲"]},{"序號":12,"國別地區":["日本"],"中文片名":"罪之聲","上映日期":"2021/07/30","申請人":"車庫娛樂股份有限公司","出品":["RELAY MOTION KFT"],"上映院數":16,"銷售票數":225,"週票數變動率":-0.5119,"銷售金額":49265,"累計銷售票數":1120,"累計銷售金額":253356,"洲別":["亞洲"]},{"序號":13,"國別地區":["日本"],"中文片名":"太陽出來之後","上映日期":"2021/07/30","申請人":"英屬蓋曼群島商威望國際娛樂股份有限公司台灣分公司","出品":["GAGA CORPORATION"],"上映院數":13,"銷售票數":76,"週票數變動率":-0.6766,"銷售金額":15200,"累計銷售票數":472,"累計銷售金額":98806,"洲別":["亞洲"]},{"序號":14,"國別地區":["法國"],"中文片名":"理髮師的男人 經典數位修復","上映日期":"2021/07/30","申請人":"天馬行空數位有限公司","出品":["TF1 DROITS AUDIOVISUELS"],"上映院數":7,"銷售票數":68,"週票數變動率":-0.5467,"銷售金額":12880,"累計銷售票數":316,"累計銷售金額":61769,"洲別":["歐洲"]},{"序號":15,"國別地區":["伊朗"],"中文片名":"淘寶少年","上映日期":"2021/07/30","申請人":"傳影互動股份有限公司","出品":["CELLULOID DREAMS SARL"],"上映院數":6,"銷售票數":55,"週票數變動率":-0.7291,"銷售金額":10100,"累計銷售票數":380,"累計銷售金額":77512,"洲別":["亞洲"]},{"序號":16,"國別地區":["法國"],"中文片名":"小王子公主心","上映日期":"2021/07/30","申請人":"東昊影業有限公司","出品":["MK2 FILMS"],"上映院數":5,"銷售票數":33,"週票數變動率":-0.6633,"銷售金額":6765,"累計銷售票數":205,"累計銷售金額":43638,"洲別":["歐洲"]},{"序號":17,"國別地區":["中國大陸"],"中文片名":"除暴","上映日期":"2021/07/30","申請人":"華藝電影有限公司","出品":["珠江影業傳媒股份有限公司","北京國影縱橫電影發行有限公司","廣東昇格傳媒股份有限公司","英皇影視文化傳媒有限公司","英皇影業有限公司","正夫影業有限公司","天津聯瑞影業有限公司","正夫君澤影視傳媒有限公司"],"上映院數":3,"銷售票數":6,"週票數變動率":-0.8636,"銷售金額":1480,"累計銷售票數":82,"累計銷售金額":19337,"洲別":["亞洲"]},{"序號":18,"國別地區":["日本"],"中文片名":"破碎的瞬間","上映日期":"2021/07/30","申請人":"可樂藝術文創股份有限公司","出品":["PONY CANYON INC"],"上映院數":3,"銷售票數":4,"週票數變動率":-0.9091,"銷售金額":880,"累計銷售票數":96,"累計銷售金額":21530,"洲別":["亞洲"]},{"序號":19,"國別地區":["美國"],"中文片名":"厲陰宅3：是惡魔逼我的","上映日期":"2021/07/22","申請人":"美商華納兄弟（遠東）股份有限公司台灣分公司","出品":["WARNER BROS PICTURES INTERNATIONAL"],"上映院數":83,"銷售票數":8604,"週票數變動率":-0.1772,"銷售金額":2233153,"累計銷售票數":43846,"累計銷售金額":11084819,"洲別":["北美洲"]},{"序號":20,"國別地區":["南韓"],"中文片名":"極速引爆","上映日期":"2021/07/22","申請人":"車庫娛樂股份有限公司","出品":["RELAY MOTION KFT"],"上映院數":16,"銷售票數":77,"週票數變動率":-0.8516,"銷售金額":19437,"累計銷售票數":5203,"累計銷售金額":1245339,"洲別":["亞洲"]},{"序號":21,"國別地區":["香港"],"中文片名":"手捲煙","上映日期":"2021/07/22","申請人":"英屬蓋曼群島商威望國際娛樂股份有限公司台灣分公司","出品":["安樂影片有限公司"],"上映院數":7,"銷售票數":47,"週票數變動率":-0.5841,"銷售金額":9765,"累計銷售票數":810,"累計銷售金額":182563,"洲別":["亞洲"]},{"序號":22,"國別地區":["日本"],"中文片名":"群青戰記","上映日期":"2021/07/22","申請人":"薩摩亞商羚邦(亞洲)有限公司台灣分公司","出品":["TOHO CO LTD"],"上映院數":4,"銷售票數":32,"週票數變動率":-0.6735,"銷售金額":7480,"累計銷售票數":776,"累計銷售金額":171612,"洲別":["亞洲"]},{"序號":23,"國別地區":["俄羅斯"],"中文片名":"宇宙特攻隊","上映日期":"2021/07/22","申請人":"捷傑有限公司","出品":["LUMINESCENCE KFT"],"上映院數":1,"銷售票數":1,"週票數變動率":-0.9,"銷售金額":270,"累計銷售票數":184,"累計銷售金額":42182,"洲別":["亞洲"]},{"序號":24,"國別地區":["西班牙"],"中文片名":"人聲","上映日期":"2021/07/17","申請人":"傳影互動股份有限公司","出品":["BATRAX ENTERTAINMENT BV"],"上映院數":9,"銷售票數":544,"週票數變動率":0.7161,"銷售金額":85035,"累計銷售票數":873,"累計銷售金額":137700,"洲別":["歐洲"]},{"序號":25,"國別地區":["日本"],"中文片名":"花束般的戀愛","上映日期":"2021/07/16","申請人":"車庫娛樂股份有限公司","出品":["RELAY MOTION KFT"],"上映院數":11,"銷售票數":584,"週票數變動率":0.2505,"銷售金額":149150,"累計銷售票數":3926,"累計銷售金額":990426,"洲別":["亞洲"]},{"序號":26,"國別地區":["法國"],"中文片名":"貝加爾湖隱居札記：在這喧囂的世界，一個人到西伯利亞森林住半年","上映日期":"2021/07/16","申請人":"水元素文化傳媒有限公司","出品":["OTHER ANGEL PICTURES"],"上映院數":5,"銷售票數":85,"週票數變動率":0.9318,"銷售金額":17265,"累計銷售票數":671,"累計銷售金額":139586,"洲別":["歐洲"]},{"序號":27,"國別地區":["美國"],"中文片名":"怪物奇兵 全新世代","上映日期":"2021/07/15","申請人":"美商華納兄弟（遠東）股份有限公司台灣分公司","出品":["WARNER BROS PICTURES INTERNATIONAL"],"上映院數":17,"銷售票數":226,"週票數變動率":-0.6983,"銷售金額":57379,"累計銷售票數":11607,"累計銷售金額":2842010,"洲別":["北美洲"]},{"序號":28,"國別地區":["美國"],"中文片名":"黑寡婦","上映日期":"2021/07/14","申請人":"台灣華特迪士尼股份有限公司","出品":["BUENA VISTA INTERNATIONAL INC"],"上映院數":88,"銷售票數":14441,"週票數變動率":-0.3173,"銷售金額":3614385,"累計銷售票數":169722,"累計銷售金額":43610639,"洲別":["北美洲"]},{"序號":29,"國別地區":["日本"],"中文片名":"燕尾蝶：數位經典版","上映日期":"2021/07/14","申請人":"光年映畫有限公司","出品":["PONY CANYON INC"],"上映院數":4,"銷售票數":164,"週票數變動率":-0.29,"銷售金額":34040,"累計銷售票數":1441,"累計銷售金額":315231,"洲別":["亞洲"]},{"序號":30,"國別地區":["南韓"],"中文片名":"韓國校園恐怖怪談：點名沒到的學生","上映日期":"2021/07/14","申請人":"水元素文化傳媒有限公司","出品":["KT HITEL CO LTD"],"上映院數":3,"銷售票數":45,"週票數變動率":0.2162,"銷售金額":11880,"累計銷售票數":967,"累計銷售金額":240552,"洲別":["亞洲"]},{"序號":31,"國別地區":["美國"],"中文片名":"失控的審判","上映日期":"2021/07/14","申請人":"英屬蓋曼群島商威望國際娛樂股份有限公司台灣分公司","出品":["STX PRODUCTIONS LLC"],"上映院數":3,"銷售票數":27,"週票數變動率":-0.7692,"銷售金額":6070,"累計銷售票數":1805,"累計銷售金額":405700,"洲別":["北美洲"]},{"序號":32,"國別地區":["法國"],"中文片名":"野蠻糾碴隊","上映日期":"2021/07/14","申請人":"天馬行空數位有限公司","出品":["INDIE SALES CO"],"上映院數":1,"銷售票數":2,"週票數變動率":-0.7143,"銷售金額":440,"累計銷售票數":227,"累計銷售金額":51676,"洲別":["歐洲"]},{"序號":33,"國別地區":["南韓"],"中文片名":"薄荷糖","上映日期":"2021/05/14","申請人":"香港商甲上娛樂有限公司台灣分公司","出品":["FINECUT CO LTD"],"上映院數":9,"銷售票數":1210,"週票數變動率":1.3048,"銷售金額":256404,"累計銷售票數":2287,"累計銷售金額":482764,"洲別":["亞洲"]},{"序號":34,"國別地區":["日本"],"中文片名":"LIP×LIP 享受這世界的方法","上映日期":"2021/05/14","申請人":"可樂藝術文創股份有限公司","出品":["TOEI COMPANY LTD"],"上映院數":9,"銷售票數":96,"週票數變動率":-0.4251,"銷售金額":22295,"累計銷售票數":793,"累計銷售金額":187822,"洲別":["亞洲"]},{"序號":35,"國別地區":["美國"],"中文片名":"死亡漩渦：奪魂鋸新遊戲","上映日期":"2021/05/12","申請人":"英屬蓋曼群島商威望國際娛樂股份有限公司台灣分公司","出品":["LIONS GATE INTERNATIONAL LTD"],"上映院數":2,"銷售票數":10,"週票數變動率":-0.7778,"銷售金額":2840,"累計銷售票數":16008,"累計銷售金額":3786120,"洲別":["北美洲"]},{"序號":36,"國別地區":["法國"],"中文片名":"人生檔案求刪除","上映日期":"2021/05/07","申請人":"光年映畫有限公司","出品":["WILD BUNCH INTERNATIONAL"],"上映院數":1,"銷售票數":3,"週票數變動率":0,"銷售金額":270,"累計銷售票數":997,"累計銷售金額":218119,"洲別":["歐洲"]},{"序號":37,"國別地區":["中華民國"],"中文片名":"非法母親","上映日期":"2021/04/30","申請人":"車庫娛樂股份有限公司","出品":["後場音像紀錄工作室有限公司"],"上映院數":1,"銷售票數":210,"週票數變動率":0.2575,"銷售金額":33600,"累計銷售票數":2251,"累計銷售金額":320343,"洲別":["亞洲"]},{"序號":38,"國別地區":["美國"],"中文片名":"玩命鈔劫","上映日期":"2021/04/29","申請人":"車庫娛樂股份有限公司","出品":["MIRAMAX DISTRIBUTION SERVICES LLC"],"上映院數":7,"銷售票數":807,"週票數變動率":1.2605,"銷售金額":229990,"累計銷售票數":329545,"累計銷售金額":81868136,"洲別":["北美洲"]},{"序號":39,"國別地區":["美國"],"中文片名":"一級任務","上映日期":"2021/04/29","申請人":"海樂影業股份有限公司","出品":["ACCELERATED GLOBAL CONTENT LLC"],"上映院數":1,"銷售票數":59,"週票數變動率":0.5946,"銷售金額":3245,"累計銷售票數":6524,"累計銷售金額":1437447,"洲別":["北美洲"]},{"序號":40,"國別地區":["日本"],"中文片名":"真．鮫島事件","上映日期":"2021/04/23","申請人":"海樂影業股份有限公司","出品":["NIKKATSU CORPORATION"],"上映院數":1,"銷售票數":24,"週票數變動率":-0.1429,"銷售金額":1320,"累計銷售票數":1126,"累計銷售金額":247318,"洲別":["亞洲"]},{"序號":41,"國別地區":["美國"],"中文片名":"搖滾農莊錄音趣","上映日期":"2021/04/23","申請人":"造次文化有限公司","出品":["AUTLOOK FILM"],"上映院數":1,"銷售票數":4,"週票數變動率":0.3333,"銷售金額":815,"累計銷售票數":2603,"累計銷售金額":620089,"洲別":["北美洲"]},{"序號":42,"國別地區":["日本"],"中文片名":"名偵探柯南 緋色的彈丸","上映日期":"2021/04/16","申請人":"向洋影業有限公司","出品":["株式会社トムス・エンタテインメント"],"上映院數":7,"銷售票數":378,"週票數變動率":0.2642,"銷售金額":100245,"累計銷售票數":274810,"累計銷售金額":65229041,"洲別":["亞洲"]},{"序號":43,"國別地區":["中華民國"],"中文片名":"聽見歌 再唱","上映日期":"2021/04/16","申請人":"美商華納兄弟（遠東）股份有限公司台灣分公司","出品":["美商華納兄弟股份有限公司台灣分公司","香港商福斯傳媒有限公司台灣分公司","海樂影業股份有限公司","有得電影有限公司","高雄人","十三月股份有限公司"],"上映院數":2,"銷售票數":66,"週票數變動率":-0.25,"銷售金額":14990,"累計銷售票數":355216,"累計銷售金額":82183108,"洲別":["亞洲"]},{"序號":44,"國別地區":["日本"],"中文片名":"跟著奈良美智去旅行 經典重映","上映日期":"2021/04/16","申請人":"天馬行空數位有限公司","出品":["TOHOKUSHINSHA FILM CORPORATION"],"上映院數":1,"銷售票數":2,"週票數變動率":-0.3333,"銷售金額":400,"累計銷售票數":1198,"累計銷售金額":258783,"洲別":["亞洲"]},{"序號":45,"國別地區":["南韓"],"中文片名":"永生戰","上映日期":"2021/04/12","申請人":"英屬蓋曼群島商威望國際娛樂股份有限公司台灣分公司","出品":["CJ ENM CO LTD"],"上映院數":1,"銷售票數":138,"週票數變動率":2.1364,"銷售金額":7590,"累計銷售票數":188618,"累計銷售金額":44844223,"洲別":["亞洲"]},{"序號":46,"國別地區":["美國"],"中文片名":"私刑救援","上映日期":"2021/04/09","申請人":"天馬行空數位有限公司","出品":["AMERIEAN CINEMA INSPIRES INC"],"上映院數":1,"銷售票數":19,"週票數變動率":0,"銷售金額":1690,"累計銷售票數":1740,"累計銷售金額":357301,"洲別":["北美洲"]},{"序號":47,"國別地區":["美國"],"中文片名":"殺戮輪迴","上映日期":"2021/04/09","申請人":"海樂影業股份有限公司","出品":["EPIC PICTURES GROUP INC"],"上映院數":1,"銷售票數":25,"週票數變動率":0.25,"銷售金額":1375,"累計銷售票數":1103,"累計銷售金額":237941,"洲別":["北美洲"]},{"序號":48,"國別地區":["美國"],"中文片名":"真人快打","上映日期":"2021/04/08","申請人":"美商華納兄弟（遠東）股份有限公司台灣分公司","出品":["WARNER BROS PICTURES INTERNATIONAL"],"上映院數":2,"銷售票數":98,"週票數變動率":0.3067,"銷售金額":6487,"累計銷售票數":122461,"累計銷售金額":29965616,"洲別":["北美洲"]},{"序號":49,"國別地區":["馬來西亞"],"中文片名":"南巫","上映日期":"2021/04/02","申請人":"傳影互動股份有限公司","出品":["BENED GOBAL SDN BHD"],"上映院數":1,"銷售票數":73,"週票數變動率":0.2167,"銷售金額":14235,"累計銷售票數":8487,"累計銷售金額":1998817,"洲別":["亞洲"]},{"序號":50,"國別地區":["中華民國"],"中文片名":"當男人戀愛時","上映日期":"2021/04/01","申請人":"金盞花大影業股份有限公司","出品":["金盞花大影業股份有限公司","眾合千澄影視文化傳媒有限公司"],"上映院數":9,"銷售票數":203,"週票數變動率":-0.3792,"銷售金額":52360,"累計銷售票數":1696605,"累計銷售金額":405380495,"洲別":["亞洲"]},{"序號":51,"國別地區":["美國"],"中文片名":"誰殺了大個子","上映日期":"2021/04/01","申請人":"華映娛樂股份有限公司","出品":["GOOD FILMS ENTERPRISES LLC"],"上映院數":3,"銷售票數":113,"週票數變動率":0.8833,"銷售金額":9340,"累計銷售票數":6525,"累計銷售金額":1468467,"洲別":["北美洲"]},{"序號":52,"國別地區":["美國"],"中文片名":"無名弒","上映日期":"2021/04/01","申請人":"美商美國環球影片股份有限公司台灣分公司","出品":["UNIVERSAL INTERNATIONAL FILMS LLC"],"上映院數":2,"銷售票數":108,"週票數變動率":0.0385,"銷售金額":8375,"累計銷售票數":104465,"累計銷售金額":24528045,"洲別":["北美洲"]},{"序號":53,"國別地區":["法國"],"中文片名":"警慌失措","上映日期":"2021/04/01","申請人":"英屬維京群島商高捷全球開發有限公司 台灣分公司","出品":["STUDIOCANAL SAS"],"上映院數":2,"銷售票數":30,"週票數變動率":-0.4915,"銷售金額":3440,"累計銷售票數":6692,"累計銷售金額":1530191,"洲別":["歐洲"]},{"序號":54,"國別地區":["美國"],"中文片名":"游牧人生","上映日期":"2021/03/19","申請人":"博偉電影股份有限公司","出品":["BUENA VISTA INTERNATIONAL INC"],"上映院數":2,"銷售票數":174,"週票數變動率":4.2727,"銷售金額":14216,"累計銷售票數":70661,"累計銷售金額":16782731,"洲別":["北美洲"]},{"序號":55,"國別地區":["美國"],"中文片名":"花漾女子","上映日期":"2021/03/12","申請人":"美商美國環球影片股份有限公司台灣分公司","出品":["UNIVERSAL INTERNATIONAL FILMS LLC"],"上映院數":3,"銷售票數":141,"週票數變動率":1.4737,"銷售金額":12363,"累計銷售票數":31941,"累計銷售金額":7509641,"洲別":["北美洲"]},{"序號":56,"國別地區":["南韓"],"中文片名":"今天決定我愛你","上映日期":"2021/03/12","申請人":"華映娛樂股份有限公司","出品":["ACEMAKER MOVIE WORKS"],"上映院數":1,"銷售票數":12,"週票數變動率":0.2,"銷售金額":1320,"累計銷售票數":13481,"累計銷售金額":3115813,"洲別":["亞洲"]},{"序號":57,"國別地區":["中華民國"],"中文片名":"揭大歡喜","上映日期":"2021/03/12","申請人":"紅色製作有限公司","出品":["紅色製作有限公司","中環國際娛樂事業股份有限公司","海鵬影業有限公司","羅特國際製作股份有限公司"],"上映院數":1,"銷售票數":6,"週票數變動率":-0.5,"銷售金額":330,"累計銷售票數":10036,"累計銷售金額":2286696,"洲別":["亞洲"]},{"序號":58,"國別地區":["美國"],"中文片名":"尋龍使者：拉雅","上映日期":"2021/03/05","申請人":"台灣華特迪士尼股份有限公司","出品":["BUENA VISTA INTERNATIONAL INC"],"上映院數":1,"銷售票數":66,"週票數變動率":0,"銷售金額":3630,"累計銷售票數":250509,"累計銷售金額":60504885,"洲別":["北美洲"]},{"序號":59,"國別地區":["丹麥"],"中文片名":"醉好的時光","上映日期":"2021/03/05","申請人":"好威映象有限公司","出品":["TRUSTNORDISK"],"上映院數":1,"銷售票數":6,"週票數變動率":0,"銷售金額":500,"累計銷售票數":18021,"累計銷售金額":4251838,"洲別":["歐洲"]},{"序號":60,"國別地區":["中華民國"],"中文片名":"東經北緯","上映日期":"2021/03/05","申請人":"英屬蓋曼群島商威望國際娛樂股份有限公司台灣分公司","出品":["緒虎製作有限公司","金騰國際傳媒股份有限公司","墨爾有限公司","德安信股份有限公司","三皇生物科技股份有限公司"],"上映院數":1,"銷售票數":1,"週票數變動率":-0.9333,"銷售金額":90,"累計銷售票數":13486,"累計銷售金額":3117603,"洲別":["亞洲"]},{"序號":61,"國別地區":["中華民國"],"中文片名":"複身犯","上映日期":"2021/02/26","申請人":"犢影制作電影有限公司","出品":["犢影制作電影有限公司","樂到家國際娛樂股份有限公司","良人行影業有限公司","麻吉砥加電影有限公司"],"上映院數":1,"銷售票數":12,"週票數變動率":0.0909,"銷售金額":1320,"累計銷售票數":63103,"累計銷售金額":14675168,"洲別":["亞洲"]},{"序號":62,"國別地區":["中國大陸"],"中文片名":"刺殺小說家","上映日期":"2021/02/26","申請人":"原創娛樂股份有限公司","出品":["抖音文化有限公司","東方嘉影電視院線傳媒股份公司","華策影業有限公司","深圳市一怡以藝文化傳媒有限公司","郭帆文化傳媒有限公司","天津十間影視傳媒有限公司","中青新影文化傳媒有限公司","天津貓眼微影文化傳媒有限公司","廣東優創合影文化傳播股份有限公司","之升影業有限公司","融創未來文化娛樂有限公司","霍爾果斯聚合影聯文化傳媒有限公司","上海阿里巴巴影業有限公司","北京自由酷鯨影業有限公司","上海尚世影業有限公司","優酷電影有限公司"],"上映院數":1,"銷售票數":4,"週票數變動率":0,"銷售金額":440,"累計銷售票數":16788,"累計銷售金額":3875069,"洲別":["亞洲"]},{"序號":63,"國別地區":["新加坡"],"中文片名":"男兒王","上映日期":"2021/02/10","申請人":"光年映畫有限公司","出品":["滿滿額娛樂股份有限公司"],"上映院數":1,"銷售票數":56,"週票數變動率":1.24,"銷售金額":6226,"累計銷售票數":15641,"累計銷售金額":3457355,"洲別":["亞洲"]},{"序號":64,"國別地區":["美國"],"中文片名":"湯姆貓與傑利鼠","上映日期":"2021/02/10","申請人":"美商華納兄弟（遠東）股份有限公司台灣分公司","出品":["WARNER BROS PICTURES INTERNATIONAL"],"上映院數":1,"銷售票數":19,"週票數變動率":-0.1364,"銷售金額":2090,"累計銷售票數":121500,"累計銷售金額":28295057,"洲別":["北美洲"]},{"序號":65,"國別地區":["中華民國"],"中文片名":"我沒有談的那場戀愛","上映日期":"2021/02/10","申請人":"南人電影有限公司","出品":["可米傳媒事業股份有限公司","海納百川娛樂有限公司","親愛的工作室有限公司","鏡文學股份有限公司","原點概念有限公司","華文創股份有限公司","南人電影有限公司"],"上映院數":1,"銷售票數":0,"週票數變動率":-1,"銷售金額":0,"累計銷售票數":159799,"累計銷售金額":38015678,"洲別":["亞洲"]},{"序號":66,"國別地區":["中華民國"],"中文片名":"角頭－浪流連","上映日期":"2021/02/05","申請人":"威視股份有限公司","出品":["巧克麗娛樂股份有限公司","台北市電影委員會"],"上映院數":2,"銷售票數":60,"週票數變動率":6.5,"銷售金額":5800,"累計銷售票數":683631,"累計銷售金額":161756545,"洲別":["亞洲"]},{"序號":67,"國別地區":["美國"],"中文片名":"靈魂急轉彎","上映日期":"2020/12/25","申請人":"台灣華特迪士尼股份有限公司","出品":["BUENA VISTA INTERNATIONAL INC"],"上映院數":3,"銷售票數":40,"週票數變動率":1,"銷售金額":3780,"累計銷售票數":768164,"累計銷售金額":184653736,"洲別":["北美洲"]},{"序號":68,"國別地區":["南韓"],"中文片名":"綠洲：數位經典版","上映日期":"2020/11/06","申請人":"光年映畫有限公司","出品":["FINECUT CO LTD"],"上映院數":1,"銷售票數":21,"週票數變動率":-0.125,"銷售金額":4570,"累計銷售票數":4651,"累計銷售金額":1045315,"洲別":["亞洲"]},{"序號":69,"國別地區":["中國大陸"],"中文片名":"蘇州河","上映日期":"2020/08/28","申請人":"前景娛樂有限公司","出品":["SOCIÉTÉ PARISIENNE DE PRODUCTION SARL"],"上映院數":1,"銷售票數":78,"週票數變動率":0,"銷售金額":15330,"累計銷售票數":8793,"累計銷售金額":1959576,"洲別":["亞洲"]},{"序號":70,"國別地區":["南韓"],"中文片名":"密陽","上映日期":"2019/02/28","申請人":"華聯國際影音股份有限公司","出品":["CJ E & M CORPORATION"],"上映院數":1,"銷售票數":41,"週票數變動率":0,"銷售金額":8800,"累計銷售票數":1347,"累計銷售金額":284291,"洲別":["亞洲"]},{"序號":71,"國別地區":["南韓"],"中文片名":"燃燒烈愛","上映日期":"2018/06/29","申請人":"華聯國際影音股份有限公司","出品":["FINECUT CO LTD"],"上映院數":1,"銷售票數":57,"週票數變動率":0.1633,"銷售金額":12700,"累計銷售票數":8504,"累計銷售金額":1845253,"洲別":["亞洲"]},{"序號":72,"國別地區":["法國"],"中文片名":"雙面薇若妮卡 經典數位修復","上映日期":"2016/07/16","申請人":"天馬行空數位有限公司","出品":["MK2-SOCIÉTÉ PAR ACTIONS SIMPLIFIÉE"],"上映院數":5,"銷售票數":439,"週票數變動率":1.1311,"銷售金額":88918,"累計銷售票數":708,"累計銷售金額":143443,"洲別":["歐洲"]}]